{
  "batch_id": "batch-014",
  "batch_index": 14,
  "batch_size": 3,
  "generated_at": "2026-07-07 07:57:25",
  "output_root": "reports/public-equity-batch/2026-07-07",
  "source_reports": [
    "reports/news/2026-07-07_kol_news_decision_report.md"
  ],
  "workflow": [
    "company-tearsheet",
    "comps-valuation",
    "initiating-coverage",
    "portfolio-risk-management"
  ],
  "items": [
    {
      "market_key": "us",
      "market": "美股",
      "symbol": "QQQ",
      "company": "納斯達克",
      "industry": "科技ETF",
      "canonical_category": "wait_entry",
      "canonical_category_label": "現在不能買，但值得等買點名單",
      "source_priority": 3,
      "instrument_type": "fund_or_etf",
      "output_subdir": "us-QQQ",
      "instrument": {
        "symbol": "QQQ",
        "market_key": "us",
        "market": "美股",
        "exchange": "NYSEARCA",
        "currency": "USD",
        "provider_symbol": "QQQ",
        "instrument_type": "fund_or_etf",
        "status": "unsupported_equity_model",
        "official_validation_status": "not_checked",
        "equity_model_supported": false,
        "warnings": [],
        "output_subdir": "us-QQQ"
      },
      "exchange": "NYSEARCA",
      "currency": "USD",
      "provider_symbol": "QQQ",
      "identity_status": "unsupported_equity_model",
      "official_validation_status": "not_checked",
      "equity_model_supported": false,
      "instrument_warnings": [],
      "industry_thesis_gate": null,
      "industry_thesis_gate_label": null,
      "hype_risk": null,
      "hype_risk_label": null,
      "industry_thesis_summary": "",
      "industry_thesis_missing_evidence": [],
      "industry_thesis_source": "",
      "model_portfolio": {
        "portfolio_units": 100,
        "long_only": true,
        "leverage_allowed": false,
        "single_name_cap": 0.05,
        "risk_budget_initial": 0.0,
        "risk_budget_post_trigger": 0.005,
        "sizing_formula": "min(single-name cap, risk budget / downside_or_stop_distance, liquidity cap)"
      },
      "sources": [
        {
          "lane": "kol",
          "lane_label": "KOL/news",
          "category": "wait_entry",
          "category_label": "現在不能買，但值得等買點名單",
          "report_path": "reports/news/2026-07-07_kol_news_decision_report.md",
          "row_index": 22,
          "expanded_index": 0,
          "raw_market": "美股",
          "raw_symbol_cell": "QQQ",
          "raw_company_cell": "納斯達克 (推論)",
          "raw_row": {
            "市場": "美股",
            "股票代號": "QQQ",
            "公司名稱": "納斯達克 (推論)",
            "產業": "科技ETF",
            "來源提及程度": "美股交易員提及",
            "來源主觀看法": "中性觀察",
            "布局建議": "高位震盪，等待財報季後方向明朗",
            "持倉建議": "觀望 (推論)",
            "追蹤指標": "大型科技股財報",
            "風險": "夏季交投清淡、高位震盪"
          }
        }
      ]
    },
    {
      "market_key": "us",
      "market": "美股",
      "symbol": "SNDK",
      "company": "閃迪",
      "industry": "記憶體",
      "canonical_category": "wait_entry",
      "canonical_category_label": "現在不能買，但值得等買點名單",
      "source_priority": 3,
      "instrument_type": "common_equity",
      "output_subdir": "us-SNDK",
      "instrument": {
        "symbol": "SNDK",
        "market_key": "us",
        "market": "美股",
        "exchange": "US",
        "currency": "USD",
        "provider_symbol": "SNDK",
        "instrument_type": "common_equity",
        "status": "ok",
        "official_validation_status": "not_checked",
        "equity_model_supported": true,
        "warnings": [],
        "output_subdir": "us-SNDK"
      },
      "exchange": "US",
      "currency": "USD",
      "provider_symbol": "SNDK",
      "identity_status": "ok",
      "official_validation_status": "not_checked",
      "equity_model_supported": true,
      "instrument_warnings": [],
      "industry_thesis_gate": null,
      "industry_thesis_gate_label": null,
      "hype_risk": null,
      "hype_risk_label": null,
      "industry_thesis_summary": "",
      "industry_thesis_missing_evidence": [],
      "industry_thesis_source": "",
      "model_portfolio": {
        "portfolio_units": 100,
        "long_only": true,
        "leverage_allowed": false,
        "single_name_cap": 0.05,
        "risk_budget_initial": 0.0,
        "risk_budget_post_trigger": 0.005,
        "sizing_formula": "min(single-name cap, risk budget / downside_or_stop_distance, liquidity cap)"
      },
      "sources": [
        {
          "lane": "kol",
          "lane_label": "KOL/news",
          "category": "wait_entry",
          "category_label": "現在不能買，但值得等買點名單",
          "report_path": "reports/news/2026-07-07_kol_news_decision_report.md",
          "row_index": 23,
          "expanded_index": 0,
          "raw_market": "美股",
          "raw_symbol_cell": "SNDK",
          "raw_company_cell": "閃迪",
          "raw_row": {
            "市場": "美股",
            "股票代號": "SNDK",
            "公司名稱": "閃迪",
            "產業": "記憶體",
            "來源提及程度": "交易員/NaNa提及",
            "來源主觀看法": "偏多",
            "布局建議": "等跌至1300-1400支撐區再買",
            "持倉建議": "中長線",
            "追蹤指標": "記憶體合約價",
            "風險": "乖離過高、短線回調風險"
          }
        }
      ]
    },
    {
      "market_key": "us",
      "market": "美股",
      "symbol": "SOXX",
      "company": "費半",
      "industry": "半導體ETF",
      "canonical_category": "wait_entry",
      "canonical_category_label": "現在不能買，但值得等買點名單",
      "source_priority": 3,
      "instrument_type": "fund_or_etf",
      "output_subdir": "us-SOXX",
      "instrument": {
        "symbol": "SOXX",
        "market_key": "us",
        "market": "美股",
        "exchange": "NYSEARCA",
        "currency": "USD",
        "provider_symbol": "SOXX",
        "instrument_type": "fund_or_etf",
        "status": "unsupported_equity_model",
        "official_validation_status": "not_checked",
        "equity_model_supported": false,
        "warnings": [],
        "output_subdir": "us-SOXX"
      },
      "exchange": "NYSEARCA",
      "currency": "USD",
      "provider_symbol": "SOXX",
      "identity_status": "unsupported_equity_model",
      "official_validation_status": "not_checked",
      "equity_model_supported": false,
      "instrument_warnings": [],
      "industry_thesis_gate": null,
      "industry_thesis_gate_label": null,
      "hype_risk": null,
      "hype_risk_label": null,
      "industry_thesis_summary": "",
      "industry_thesis_missing_evidence": [],
      "industry_thesis_source": "",
      "model_portfolio": {
        "portfolio_units": 100,
        "long_only": true,
        "leverage_allowed": false,
        "single_name_cap": 0.05,
        "risk_budget_initial": 0.0,
        "risk_budget_post_trigger": 0.005,
        "sizing_formula": "min(single-name cap, risk budget / downside_or_stop_distance, liquidity cap)"
      },
      "sources": [
        {
          "lane": "kol",
          "lane_label": "KOL/news",
          "category": "wait_entry",
          "category_label": "現在不能買，但值得等買點名單",
          "report_path": "reports/news/2026-07-07_kol_news_decision_report.md",
          "row_index": 24,
          "expanded_index": 0,
          "raw_market": "美股",
          "raw_symbol_cell": "SOXX",
          "raw_company_cell": "費半 (推論)",
          "raw_row": {
            "市場": "美股",
            "股票代號": "SOXX",
            "公司名稱": "費半 (推論)",
            "產業": "半導體ETF",
            "來源提及程度": "游庭皓/NaNa",
            "來源主觀看法": "偏多",
            "布局建議": "等站穩均線或回測季線再加碼",
            "持倉建議": "中長線",
            "追蹤指標": "AI資本開支",
            "風險": "乖離過大、量化基金回撤風險"
          }
        }
      ]
    }
  ]
}
