{
  "analysisTicker": "2330.TW",
  "date": "0522",
  "displayName": "台積電",
  "reviewHtml": "<h2>回顧</h2>\n<ul class=\"report-list stock-review-list\">\n<li><a href=\"#/stocks/2330/0521\"><strong>2026-05-21</strong><span>2330 股票分析</span></a></li>\n<li><a href=\"#/stocks/2330/0520\"><strong>2026-05-20</strong><span>2330 股票分析</span></a></li>\n<li><a href=\"#/stocks/2330/0519\"><strong>2026-05-19</strong><span>2330 股票分析</span></a></li>\n<li><a href=\"#/stocks/2330/0518\"><strong>2026-05-18</strong><span>2330 股票分析</span></a></li>\n<li><a href=\"#/stocks/2330/0517\"><strong>2026-05-17</strong><span>2330 股票分析</span></a></li>\n<li><a href=\"#/stocks/2330/0516\"><strong>2026-05-16</strong><span>2330 股票分析</span></a></li>\n<li><a href=\"#/stocks/2330/0515\"><strong>2026-05-15</strong><span>2330 股票分析</span></a></li>\n<li><a href=\"#/stocks/2330/0514\"><strong>2026-05-14</strong><span>2330 股票分析</span></a></li>\n<li><a href=\"#/stocks/2330/0513\"><strong>2026-05-13</strong><span>2330 股票分析</span></a></li>\n<li><a href=\"#/stocks/2330/0512\"><strong>2026-05-12</strong><span>2330 股票分析</span></a></li>\n<li><a href=\"#/stocks/2330/0511\"><strong>2026-05-11</strong><span>2330 股票分析</span></a></li>\n<li><a href=\"#/stocks/2330/0510\"><strong>2026-05-10</strong><span>2330 股票分析</span></a></li>\n<li><a href=\"#/stocks/2330/0509\"><strong>2026-05-09</strong><span>2330 股票分析</span></a></li>\n<li><a href=\"#/stocks/2330/0508\"><strong>2026-05-08</strong><span>2330 股票分析</span></a></li>\n<li><a href=\"#/stocks/2330/0507\"><strong>2026-05-07</strong><span>2330 股票分析</span></a></li>\n</ul>",
  "sourceHtml": "<ul>\n<li>| 1 | AI 基礎設施與雲端算力 (GPU, 電力, 網通) | 高 | NVDA 財報揭示資料中心佔比達 92%，網通成長 199%；NBIS 簽下微軟與 Meta 鉅額算力與電力合約。 | NVDA, AMZN, NBIS, 2330 | 資本支出過大導致融資壓力，若專案延遲交付將影響估值。 |</li>\n<li>| 2330 | 台積電 | 半導體代工 | AI 基礎設施 | 來源提及 | 壟斷高階 AI 晶片代工與 CoWoS 封裝技術，為 Google、NVDA 等巨頭首選，訂單能見度高。 | 產能持續滿載；美系大廠 AI 眼鏡晶片代工。 | 高 | 分批觀察 | 地緣政治風險；短期指數乖離過大。 |</li>\n<li>| 4 | 台股 | 2330 | 台積電 | 半導體代工 | 高 | 獨家壟斷先進製程與 CoWoS 封裝，訂單能見度極高，受惠 AI 眼鏡等新終端。 | 地緣政治風險；單一市場依賴度。 | 每月營收變化與資本支出是否持續上修。 |</li>\n<li>| 輝達財報後續法人目標價調整 | 產業動態 | NVDA 的財測是 AI 資本支出的風向球，股價若利多不漲將引發半導體估值修正疑慮。 | SOXX, 2330, AI 伺服器代工廠與零組件 |</li>\n<li>「AI 算力基礎設施（含電力與網通）」、「AI 代理與智慧終端（AI 眼鏡）」及「記憶體超週期」。台股與美股中被反覆提及的指標標的包含 NVDA、TSMC (2330)、聯發科 (2454)、NBIS 以及即將面臨 IPO 吸金效應的 SpaceX (SPCX) 與受惠的 00403A 主動式 ETF。台股較受惠於先進封裝、光學元件及主動型 ETF 資金動能，美股則受惠於 CSP（雲端服務</li>\n</ul>",
  "sourcePath": "/Users/willcoming/code/stockReport/stocks/2330/0522.html",
  "status": "完成",
  "statusLabel": "完成",
  "subtitle": "2330.TW · 完成",
  "symbol": "2330",
  "technicalChart": {
    "dataTicker": "2330.TW",
    "generatedAt": "2026-05-22T08:18:41.319651+00:00",
    "rows": [
      {
        "close": 1150,
        "date": "2025-08-21",
        "ema20": 1156.723995,
        "ema200": 1037.099146,
        "ema5": 1160.594668,
        "ema60": 1106.446742,
        "high": 1155,
        "low": 1140,
        "macd": 14.900196,
        "macd_hist": -5.658491,
        "macd_signal": 20.558687,
        "open": 1140,
        "rsi": 50.656348,
        "volume": 23424804,
        "zlsma": 1192.873264
      },
      {
        "close": 1135,
        "date": "2025-08-22",
        "ema20": 1154.655043,
        "ema200": 1038.073284,
        "ema5": 1152.063112,
        "ema60": 1107.382914,
        "high": 1155,
        "low": 1135,
        "macd": 11.485259,
        "macd_hist": -7.258742,
        "macd_signal": 18.744001,
        "open": 1155,
        "rsi": 46.984456,
        "volume": 19205763,
        "zlsma": 1188.055556
      },
      {
        "close": 1170,
        "date": "2025-08-25",
        "ema20": 1156.116468,
        "ema200": 1039.385987,
        "ema5": 1158.042075,
        "ema60": 1109.435933,
        "high": 1180,
        "low": 1160,
        "macd": 11.470875,
        "macd_hist": -5.818501,
        "macd_signal": 17.289376,
        "open": 1165,
        "rsi": 55.153099,
        "volume": 25103514,
        "zlsma": 1186.71875
      },
      {
        "close": 1175,
        "date": "2025-08-26",
        "ema20": 1157.914899,
        "ema200": 1040.735381,
        "ema5": 1163.694716,
        "ema60": 1111.585575,
        "high": 1185,
        "low": 1160,
        "macd": 11.727743,
        "macd_hist": -4.449306,
        "macd_signal": 16.177049,
        "open": 1165,
        "rsi": 56.191563,
        "volume": 35508897,
        "zlsma": 1187.517361
      },
      {
        "close": 1190,
        "date": "2025-08-27",
        "ema20": 1160.970623,
        "ema200": 1042.220601,
        "ema5": 1172.463144,
        "ema60": 1114.15654,
        "high": 1190,
        "low": 1180,
        "macd": 12.991925,
        "macd_hist": -2.548099,
        "macd_signal": 15.540024,
        "open": 1190,
        "rsi": 59.240794,
        "volume": 21952558,
        "zlsma": 1188.428819
      },
      {
        "close": 1160,
        "date": "2025-08-28",
        "ema20": 1160.878183,
        "ema200": 1043.392535,
        "ema5": 1168.308763,
        "ema60": 1115.659604,
        "high": 1185,
        "low": 1160,
        "macd": 11.441163,
        "macd_hist": -3.279089,
        "macd_signal": 14.720252,
        "open": 1185,
        "rsi": 51.517508,
        "volume": 19975237,
        "zlsma": 1186.970486
      },
      {
        "close": 1160,
        "date": "2025-08-29",
        "ema20": 1160.794546,
        "ema200": 1044.552808,
        "ema5": 1165.539175,
        "ema60": 1117.113387,
        "high": 1185,
        "low": 1160,
        "macd": 10.095794,
        "macd_hist": -3.699566,
        "macd_signal": 13.795361,
        "open": 1180,
        "rsi": 51.517508,
        "volume": 19522740,
        "zlsma": 1185.703125
      },
      {
        "close": 1165,
        "date": "2025-09-01",
        "ema20": 1161.195066,
        "ema200": 1045.751288,
        "ema5": 1165.35945,
        "ema60": 1118.68344,
        "high": 1165,
        "low": 1145,
        "macd": 9.325539,
        "macd_hist": -3.575857,
        "macd_signal": 12.901396,
        "open": 1150,
        "rsi": 52.709232,
        "volume": 22018940,
        "zlsma": 1184.982639
      },
      {
        "close": 1160,
        "date": "2025-09-02",
        "ema20": 1161.08125,
        "ema200": 1046.888091,
        "ema5": 1163.572967,
        "ema60": 1120.038082,
        "high": 1175,
        "low": 1155,
        "macd": 8.216929,
        "macd_hist": -3.747574,
        "macd_signal": 11.964503,
        "open": 1170,
        "rsi": 51.349932,
        "volume": 14037411,
        "zlsma": 1184.748264
      },
      {
        "close": 1160,
        "date": "2025-09-03",
        "ema20": 1160.978274,
        "ema200": 1048.013583,
        "ema5": 1162.381978,
        "ema60": 1121.348308,
        "high": 1160,
        "low": 1145,
        "macd": 7.254719,
        "macd_hist": -3.767827,
        "macd_signal": 11.022546,
        "open": 1155,
        "rsi": 51.349932,
        "volume": 19511981,
        "zlsma": 1182.977431
      },
      {
        "close": 1160,
        "date": "2025-09-04",
        "ema20": 1160.885105,
        "ema200": 1049.127875,
        "ema5": 1161.587985,
        "ema60": 1122.615577,
        "high": 1175,
        "low": 1160,
        "macd": 6.418176,
        "macd_hist": -3.683496,
        "macd_signal": 10.101672,
        "open": 1170,
        "rsi": 51.349932,
        "volume": 24333323,
        "zlsma": 1180.928819
      },
      {
        "close": 1180,
        "date": "2025-09-05",
        "ema20": 1162.705571,
        "ema200": 1050.430085,
        "ema5": 1167.725323,
        "ema60": 1124.497034,
        "high": 1180,
        "low": 1170,
        "macd": 7.285065,
        "macd_hist": -2.253286,
        "macd_signal": 9.538351,
        "open": 1175,
        "rsi": 56.90251,
        "volume": 27133819,
        "zlsma": 1182.682292
      },
      {
        "close": 1180,
        "date": "2025-09-08",
        "ema20": 1164.35266,
        "ema200": 1051.719338,
        "ema5": 1171.816882,
        "ema60": 1126.316803,
        "high": 1195,
        "low": 1180,
        "macd": 7.881231,
        "macd_hist": -1.325696,
        "macd_signal": 9.206927,
        "open": 1195,
        "rsi": 56.90251,
        "volume": 27281959,
        "zlsma": 1183.246528
      },
      {
        "close": 1200,
        "date": "2025-09-09",
        "ema20": 1167.747644,
        "ema200": 1053.194768,
        "ema5": 1181.211255,
        "ema60": 1128.732645,
        "high": 1200,
        "low": 1190,
        "macd": 9.853939,
        "macd_hist": 0.51761,
        "macd_signal": 9.336329,
        "open": 1195,
        "rsi": 61.94036,
        "volume": 31329096,
        "zlsma": 1187.5
      },
      {
        "close": 1225,
        "date": "2025-09-10",
        "ema20": 1173.20025,
        "ema200": 1054.904273,
        "ema5": 1195.807503,
        "ema60": 1131.888952,
        "high": 1230,
        "low": 1215,
        "macd": 13.281515,
        "macd_hist": 3.156149,
        "macd_signal": 10.125366,
        "open": 1220,
        "rsi": 67.115059,
        "volume": 39665156,
        "zlsma": 1189.331597
      },
      {
        "close": 1240,
        "date": "2025-09-11",
        "ema20": 1179.562131,
        "ema200": 1056.746021,
        "ema5": 1210.538336,
        "ema60": 1135.433577,
        "high": 1260,
        "low": 1235,
        "macd": 17.012162,
        "macd_hist": 5.509437,
        "macd_signal": 11.502726,
        "open": 1255,
        "rsi": 69.770784,
        "volume": 30345708,
        "zlsma": 1192.873264
      },
      {
        "close": 1260,
        "date": "2025-09-12",
        "ema20": 1187.22288,
        "ema200": 1058.768449,
        "ema5": 1227.025557,
        "ema60": 1139.517722,
        "high": 1260,
        "low": 1250,
        "macd": 21.336605,
        "macd_hist": 7.867104,
        "macd_signal": 13.469502,
        "open": 1255,
        "rsi": 72.911927,
        "volume": 26492972,
        "zlsma": 1197.699653
      },
      {
        "close": 1255,
        "date": "2025-09-15",
        "ema20": 1193.677844,
        "ema200": 1060.721002,
        "ema5": 1236.350371,
        "ema60": 1143.304026,
        "high": 1260,
        "low": 1250,
        "macd": 24.082689,
        "macd_hist": 8.49055,
        "macd_signal": 15.592139,
        "open": 1260,
        "rsi": 70.927656,
        "volume": 24589707,
        "zlsma": 1202.152778
      },
      {
        "close": 1280,
        "date": "2025-09-16",
        "ema20": 1201.899002,
        "ema200": 1062.902882,
        "ema5": 1250.900248,
        "ema60": 1147.785861,
        "high": 1285,
        "low": 1260,
        "macd": 27.954034,
        "macd_hist": 9.889516,
        "macd_signal": 18.064518,
        "open": 1265,
        "rsi": 74.643418,
        "volume": 40130070,
        "zlsma": 1207.074653
      },
      {
        "close": 1265,
        "date": "2025-09-17",
        "ema20": 1207.908621,
        "ema200": 1064.913799,
        "ema5": 1255.600165,
        "ema60": 1151.628948,
        "high": 1275,
        "low": 1265,
        "macd": 29.471994,
        "macd_hist": 9.125981,
        "macd_signal": 20.346013,
        "open": 1270,
        "rsi": 68.949213,
        "volume": 29283972,
        "zlsma": 1212.803819
      },
      {
        "close": 1285,
        "date": "2025-09-18",
        "ema20": 1215.250657,
        "ema200": 1067.103711,
        "ema5": 1265.40011,
        "ema60": 1156.001769,
        "high": 1285,
        "low": 1265,
        "macd": 31.920857,
        "macd_hist": 9.259875,
        "macd_signal": 22.660982,
        "open": 1275,
        "rsi": 72.014671,
        "volume": 24191307,
        "zlsma": 1219.739583
      },
      {
        "close": 1265,
        "date": "2025-09-19",
        "ema20": 1219.988689,
        "ema200": 1069.072828,
        "ema5": 1265.26674,
        "ema60": 1159.575482,
        "high": 1290,
        "low": 1265,
        "macd": 31.88027,
        "macd_hist": 7.37543,
        "macd_signal": 24.504839,
        "open": 1285,
        "rsi": 65.093997,
        "volume": 44913316,
        "zlsma": 1225.008681
      },
      {
        "close": 1295,
        "date": "2025-09-22",
        "ema20": 1227.132624,
        "ema200": 1071.32086,
        "ema5": 1275.177827,
        "ema60": 1164.01563,
        "high": 1295,
        "low": 1270,
        "macd": 33.878325,
        "macd_hist": 7.498789,
        "macd_signal": 26.379537,
        "open": 1270,
        "rsi": 69.784628,
        "volume": 28859955,
        "zlsma": 1232.300347
      },
      {
        "close": 1340,
        "date": "2025-09-23",
        "ema20": 1237.881898,
        "ema200": 1073.994284,
        "ema5": 1296.785218,
        "ema60": 1169.785609,
        "high": 1340,
        "low": 1315,
        "macd": 38.647419,
        "macd_hist": 9.814306,
        "macd_signal": 28.833113,
        "open": 1320,
        "rsi": 75.173753,
        "volume": 33953781,
        "zlsma": 1247.161458
      },
      {
        "close": 1340,
        "date": "2025-09-24",
        "ema20": 1247.607431,
        "ema200": 1076.641107,
        "ema5": 1311.190145,
        "ema60": 1175.366409,
        "high": 1355,
        "low": 1325,
        "macd": 41.943462,
        "macd_hist": 10.488279,
        "macd_signal": 31.455183,
        "open": 1350,
        "rsi": 75.173753,
        "volume": 44737182,
        "zlsma": 1260.477431
      },
      {
        "close": 1320,
        "date": "2025-09-25",
        "ema20": 1254.501962,
        "ema200": 1079.062589,
        "ema5": 1314.126763,
        "ema60": 1180.108494,
        "high": 1330,
        "low": 1320,
        "macd": 42.452402,
        "macd_hist": 8.797776,
        "macd_signal": 33.654627,
        "open": 1320,
        "rsi": 68.844581,
        "volume": 25861812,
        "zlsma": 1273.020833
      },
      {
        "close": 1300,
        "date": "2025-09-26",
        "ema20": 1258.835108,
        "ema200": 1081.260971,
        "ema5": 1309.417842,
        "ema60": 1184.039363,
        "high": 1315,
        "low": 1295,
        "macd": 40.771915,
        "macd_hist": 5.693831,
        "macd_signal": 35.078084,
        "open": 1310,
        "rsi": 63.121346,
        "volume": 25793295,
        "zlsma": 1280.789931
      },
      {
        "close": 1305,
        "date": "2025-09-30",
        "ema20": 1263.231764,
        "ema200": 1083.48723,
        "ema5": 1307.945228,
        "ema60": 1188.005285,
        "high": 1320,
        "low": 1305,
        "macd": 39.389517,
        "macd_hist": 3.449146,
        "macd_signal": 35.940371,
        "open": 1310,
        "rsi": 63.92869,
        "volume": 36642789,
        "zlsma": 1288.411458
      },
      {
        "close": 1325,
        "date": "2025-10-01",
        "ema20": 1269.114454,
        "ema200": 1085.890342,
        "ema5": 1313.630152,
        "ema60": 1192.496915,
        "high": 1350,
        "low": 1325,
        "macd": 39.453,
        "macd_hist": 2.810103,
        "macd_signal": 36.642897,
        "open": 1325,
        "rsi": 67.037199,
        "volume": 33837323,
        "zlsma": 1296.293403
      },
      {
        "close": 1365,
        "date": "2025-10-02",
        "ema20": 1278.24641,
        "ema200": 1088.667553,
        "ema5": 1330.753435,
        "ema60": 1198.152754,
        "high": 1370,
        "low": 1355,
        "macd": 42.244014,
        "macd_hist": 4.480893,
        "macd_signal": 37.76312,
        "open": 1360,
        "rsi": 72.197637,
        "volume": 29593487,
        "zlsma": 1309.678819
      },
      {
        "close": 1400,
        "date": "2025-10-03",
        "ema20": 1289.84199,
        "ema200": 1091.765388,
        "ema5": 1353.835623,
        "ema60": 1204.770697,
        "high": 1400,
        "low": 1365,
        "macd": 46.741315,
        "macd_hist": 7.182556,
        "macd_signal": 39.558759,
        "open": 1365,
        "rsi": 75.771815,
        "volume": 31032341,
        "zlsma": 1325.590278
      },
      {
        "close": 1435,
        "date": "2025-10-07",
        "ema20": 1303.666563,
        "ema200": 1095.180658,
        "ema5": 1380.890415,
        "ema60": 1212.319198,
        "high": 1445,
        "low": 1420,
        "macd": 52.5242,
        "macd_hist": 10.372352,
        "macd_signal": 42.151847,
        "open": 1420,
        "rsi": 78.718188,
        "volume": 38395572,
        "zlsma": 1343.567708
      },
      {
        "close": 1415,
        "date": "2025-10-08",
        "ema20": 1314.269747,
        "ema200": 1098.36294,
        "ema5": 1392.260277,
        "ema60": 1218.964471,
        "high": 1420,
        "low": 1405,
        "macd": 54.860942,
        "macd_hist": 10.167276,
        "macd_signal": 44.693666,
        "open": 1410,
        "rsi": 73.23736,
        "volume": 23064494,
        "zlsma": 1359.895833
      },
      {
        "close": 1440,
        "date": "2025-10-09",
        "ema20": 1326.244057,
        "ema200": 1101.762314,
        "ema5": 1408.173518,
        "ema60": 1226.211537,
        "high": 1455,
        "low": 1430,
        "macd": 58.060829,
        "macd_hist": 10.69373,
        "macd_signal": 47.367099,
        "open": 1440,
        "rsi": 75.530791,
        "volume": 39052134,
        "zlsma": 1377.829861
      },
      {
        "close": 1415,
        "date": "2025-10-13",
        "ema20": 1334.697004,
        "ema200": 1104.879106,
        "ema5": 1410.449012,
        "ema60": 1232.401323,
        "high": 1420,
        "low": 1390,
        "macd": 57.911899,
        "macd_hist": 8.43584,
        "macd_signal": 49.476059,
        "open": 1390,
        "rsi": 69.149205,
        "volume": 53850992,
        "zlsma": 1393.237847
      },
      {
        "close": 1425,
        "date": "2025-10-14",
        "ema20": 1343.297289,
        "ema200": 1108.064389,
        "ema5": 1415.299341,
        "ema60": 1238.716033,
        "high": 1460,
        "low": 1420,
        "macd": 57.932972,
        "macd_hist": 6.765531,
        "macd_signal": 51.167441,
        "open": 1455,
        "rsi": 70.232608,
        "volume": 39889256,
        "zlsma": 1407.465278
      },
      {
        "close": 1465,
        "date": "2025-10-15",
        "ema20": 1354.888024,
        "ema200": 1111.615987,
        "ema5": 1431.866228,
        "ema60": 1246.13518,
        "high": 1465,
        "low": 1425,
        "macd": 60.480161,
        "macd_hist": 7.450176,
        "macd_signal": 53.029985,
        "open": 1435,
        "rsi": 74.143987,
        "volume": 41056405,
        "zlsma": 1424.583333
      },
      {
        "close": 1485,
        "date": "2025-10-16",
        "ema20": 1367.27964,
        "ema200": 1115.331251,
        "ema5": 1449.577485,
        "ema60": 1253.966813,
        "high": 1495,
        "low": 1465,
        "macd": 63.38203,
        "macd_hist": 8.281636,
        "macd_signal": 55.100394,
        "open": 1465,
        "rsi": 75.852492,
        "volume": 37737678,
        "zlsma": 1441.336806
      },
      {
        "close": 1450,
        "date": "2025-10-17",
        "ema20": 1375.15777,
        "ema200": 1118.661288,
        "ema5": 1449.718323,
        "ema60": 1260.394131,
        "high": 1465,
        "low": 1450,
        "macd": 62.14125,
        "macd_hist": 5.632685,
        "macd_signal": 56.508565,
        "open": 1455,
        "rsi": 67.45256,
        "volume": 38077331,
        "zlsma": 1452.777778
      },
      {
        "close": 1480,
        "date": "2025-10-20",
        "ema20": 1385.142744,
        "ema200": 1122.256698,
        "ema5": 1459.812216,
        "ema60": 1267.594323,
        "high": 1495,
        "low": 1455,
        "macd": 62.854128,
        "macd_hist": 5.07645,
        "macd_signal": 57.777678,
        "open": 1460,
        "rsi": 70.471063,
        "volume": 33015553,
        "zlsma": 1465.164931
      },
      {
        "close": 1480,
        "date": "2025-10-21",
        "ema20": 1394.176769,
        "ema200": 1125.816333,
        "ema5": 1466.541477,
        "ema60": 1274.558444,
        "high": 1500,
        "low": 1480,
        "macd": 62.696365,
        "macd_hist": 3.93495,
        "macd_signal": 58.761415,
        "open": 1485,
        "rsi": 70.471063,
        "volume": 34601251,
        "zlsma": 1475.642361
      },
      {
        "close": 1460,
        "date": "2025-10-22",
        "ema20": 1400.445648,
        "ema200": 1129.141544,
        "ema5": 1464.360985,
        "ema60": 1280.638495,
        "high": 1470,
        "low": 1455,
        "macd": 60.262831,
        "macd_hist": 1.201133,
        "macd_signal": 59.061699,
        "open": 1460,
        "rsi": 65.755993,
        "volume": 27360948,
        "zlsma": 1484.644097
      },
      {
        "close": 1450,
        "date": "2025-10-23",
        "ema20": 1405.16511,
        "ema200": 1132.334165,
        "ema5": 1459.57399,
        "ema60": 1286.191331,
        "high": 1455,
        "low": 1435,
        "macd": 56.87174,
        "macd_hist": -1.751967,
        "macd_signal": 58.623707,
        "open": 1440,
        "rsi": 63.469361,
        "volume": 23570046,
        "zlsma": 1490.572917
      },
      {
        "close": 1480,
        "date": "2025-10-27",
        "ema20": 1412.292242,
        "ema200": 1135.793527,
        "ema5": 1466.38266,
        "ema60": 1292.545714,
        "high": 1500,
        "low": 1480,
        "macd": 55.959953,
        "macd_hist": -2.131003,
        "macd_signal": 58.090956,
        "open": 1500,
        "rsi": 67.158995,
        "volume": 32851952,
        "zlsma": 1500.034722
      },
      {
        "close": 1475,
        "date": "2025-10-28",
        "ema20": 1418.26441,
        "ema200": 1139.168716,
        "ema5": 1469.255107,
        "ema60": 1298.527822,
        "high": 1490,
        "low": 1470,
        "macd": 54.20901,
        "macd_hist": -3.105557,
        "macd_signal": 57.314567,
        "open": 1480,
        "rsi": 65.963188,
        "volume": 28381919,
        "zlsma": 1507.265625
      },
      {
        "close": 1505,
        "date": "2025-10-29",
        "ema20": 1426.524942,
        "ema200": 1142.808828,
        "ema5": 1481.170071,
        "ema60": 1305.297401,
        "high": 1515,
        "low": 1490,
        "macd": 54.612584,
        "macd_hist": -2.161586,
        "macd_signal": 56.77417,
        "open": 1495,
        "rsi": 69.475125,
        "volume": 30631103,
        "zlsma": 1518.394097
      },
      {
        "close": 1505,
        "date": "2025-10-30",
        "ema20": 1433.998757,
        "ema200": 1146.41272,
        "ema5": 1489.113381,
        "ema60": 1311.845027,
        "high": 1520,
        "low": 1500,
        "macd": 54.306409,
        "macd_hist": -1.974209,
        "macd_signal": 56.280618,
        "open": 1515,
        "rsi": 69.475125,
        "volume": 27867757,
        "zlsma": 1526.848958
      },
      {
        "close": 1500,
        "date": "2025-10-31",
        "ema20": 1440.28459,
        "ema200": 1149.931001,
        "ema5": 1492.742254,
        "ema60": 1318.014043,
        "high": 1525,
        "low": 1500,
        "macd": 53.048791,
        "macd_hist": -2.585461,
        "macd_signal": 55.634252,
        "open": 1515,
        "rsi": 68.116596,
        "volume": 31928423,
        "zlsma": 1531.215278
      },
      {
        "close": 1510,
        "date": "2025-11-03",
        "ema20": 1446.924153,
        "ema200": 1153.513778,
        "ema5": 1498.494836,
        "ema60": 1324.308664,
        "high": 1520,
        "low": 1490,
        "macd": 52.256654,
        "macd_hist": -2.702079,
        "macd_signal": 54.958733,
        "open": 1510,
        "rsi": 69.405149,
        "volume": 29118770,
        "zlsma": 1536.449653
      },
      {
        "close": 1505,
        "date": "2025-11-04",
        "ema20": 1452.455186,
        "ema200": 1157.011153,
        "ema5": 1500.663224,
        "ema60": 1330.23297,
        "high": 1525,
        "low": 1495,
        "macd": 50.641656,
        "macd_hist": -3.453661,
        "macd_signal": 54.095318,
        "open": 1520,
        "rsi": 67.926945,
        "volume": 33925673,
        "zlsma": 1542.934028
      },
      {
        "close": 1460,
        "date": "2025-11-05",
        "ema20": 1453.173739,
        "ema200": 1160.025967,
        "ema5": 1487.108816,
        "ema60": 1334.487627,
        "high": 1485,
        "low": 1455,
        "macd": 45.209488,
        "macd_hist": -7.108663,
        "macd_signal": 52.318152,
        "open": 1480,
        "rsi": 56.304151,
        "volume": 56305422,
        "zlsma": 1547.282986
      },
      {
        "close": 1465,
        "date": "2025-11-06",
        "ema20": 1454.30005,
        "ema200": 1163.060535,
        "ema5": 1479.739211,
        "ema60": 1338.766721,
        "high": 1480,
        "low": 1465,
        "macd": 40.837169,
        "macd_hist": -9.184786,
        "macd_signal": 50.021955,
        "open": 1470,
        "rsi": 57.180846,
        "volume": 27411394,
        "zlsma": 1551.579861
      },
      {
        "close": 1460,
        "date": "2025-11-07",
        "ema20": 1454.842902,
        "ema200": 1166.015156,
        "ema5": 1473.159474,
        "ema60": 1342.741583,
        "high": 1465,
        "low": 1455,
        "macd": 36.547321,
        "macd_hist": -10.779707,
        "macd_signal": 47.327028,
        "open": 1460,
        "rsi": 55.971474,
        "volume": 20329390,
        "zlsma": 1553.793403
      },
      {
        "close": 1475,
        "date": "2025-11-10",
        "ema20": 1456.762626,
        "ema200": 1169.089632,
        "ema5": 1473.772983,
        "ema60": 1347.077924,
        "high": 1485,
        "low": 1465,
        "macd": 33.966416,
        "macd_hist": -10.688489,
        "macd_signal": 44.654906,
        "open": 1470,
        "rsi": 58.787546,
        "volume": 25281744,
        "zlsma": 1554.088542
      },
      {
        "close": 1465,
        "date": "2025-11-11",
        "ema20": 1457.547138,
        "ema200": 1172.034014,
        "ema5": 1470.848655,
        "ema60": 1350.944222,
        "high": 1495,
        "low": 1465,
        "macd": 30.759538,
        "macd_hist": -11.116294,
        "macd_signal": 41.875832,
        "open": 1490,
        "rsi": 56.206535,
        "volume": 22444166,
        "zlsma": 1550.9375
      },
      {
        "close": 1475,
        "date": "2025-11-12",
        "ema20": 1459.209315,
        "ema200": 1175.048601,
        "ema5": 1472.232437,
        "ema60": 1355.011625,
        "high": 1485,
        "low": 1460,
        "macd": 28.694211,
        "macd_hist": -10.545297,
        "macd_signal": 39.239508,
        "open": 1470,
        "rsi": 58.183665,
        "volume": 23642502,
        "zlsma": 1546.102431
      },
      {
        "close": 1460,
        "date": "2025-11-13",
        "ema20": 1459.284618,
        "ema200": 1177.883938,
        "ema5": 1468.154958,
        "ema60": 1358.453866,
        "high": 1470,
        "low": 1460,
        "macd": 25.552497,
        "macd_hist": -10.949609,
        "macd_signal": 36.502106,
        "open": 1460,
        "rsi": 54.228798,
        "volume": 21255597,
        "zlsma": 1542.048611
      },
      {
        "close": 1430,
        "date": "2025-11-14",
        "ema20": 1456.495607,
        "ema200": 1180.392556,
        "ema5": 1455.436639,
        "ema60": 1360.799641,
        "high": 1440,
        "low": 1425,
        "macd": 20.406681,
        "macd_hist": -12.87634,
        "macd_signal": 33.283021,
        "open": 1425,
        "rsi": 47.303497,
        "volume": 26861702,
        "zlsma": 1533.914931
      },
      {
        "close": 1445,
        "date": "2025-11-17",
        "ema20": 1455.400787,
        "ema200": 1183.025466,
        "ema5": 1451.957759,
        "ema60": 1363.560309,
        "high": 1460,
        "low": 1445,
        "macd": 17.339085,
        "macd_hist": -12.755149,
        "macd_signal": 30.094234,
        "open": 1450,
        "rsi": 50.693993,
        "volume": 26602730,
        "zlsma": 1529.505208
      },
      {
        "close": 1405,
        "date": "2025-11-18",
        "ema20": 1450.600712,
        "ema200": 1185.234168,
        "ema5": 1436.305173,
        "ema60": 1364.918987,
        "high": 1435,
        "low": 1405,
        "macd": 11.547218,
        "macd_hist": -14.837612,
        "macd_signal": 26.38483,
        "open": 1435,
        "rsi": 42.787994,
        "volume": 42198432,
        "zlsma": 1521.388889
      },
      {
        "close": 1395,
        "date": "2025-11-19",
        "ema20": 1445.305406,
        "ema200": 1187.32139,
        "ema5": 1422.536782,
        "ema60": 1365.90525,
        "high": 1415,
        "low": 1395,
        "macd": 6.080118,
        "macd_hist": -16.24377,
        "macd_signal": 22.323888,
        "open": 1400,
        "rsi": 41.063808,
        "volume": 35591948,
        "zlsma": 1509.722222
      },
      {
        "close": 1455,
        "date": "2025-11-20",
        "ema20": 1446.228701,
        "ema200": 1189.984859,
        "ema5": 1433.357855,
        "ema60": 1368.826389,
        "high": 1460,
        "low": 1440,
        "macd": 6.513813,
        "macd_hist": -12.64806,
        "macd_signal": 19.161873,
        "open": 1450,
        "rsi": 53.239136,
        "volume": 25964403,
        "zlsma": 1501.935764
      },
      {
        "close": 1385,
        "date": "2025-11-21",
        "ema20": 1440.397396,
        "ema200": 1191.925308,
        "ema5": 1417.23857,
        "ema60": 1369.356672,
        "high": 1405,
        "low": 1385,
        "macd": 1.195325,
        "macd_hist": -14.373238,
        "macd_signal": 15.568563,
        "open": 1395,
        "rsi": 42.268197,
        "volume": 54518246,
        "zlsma": 1491.736111
      },
      {
        "close": 1375,
        "date": "2025-11-24",
        "ema20": 1434.169073,
        "ema200": 1193.746947,
        "ema5": 1403.159046,
        "ema60": 1369.541699,
        "high": 1405,
        "low": 1375,
        "macd": -3.782924,
        "macd_hist": -15.48119,
        "macd_signal": 11.698266,
        "open": 1400,
        "rsi": 40.969348,
        "volume": 79134658,
        "zlsma": 1478.802083
      },
      {
        "close": 1415,
        "date": "2025-11-25",
        "ema20": 1432.343447,
        "ema200": 1195.948469,
        "ema5": 1407.106031,
        "ema60": 1371.032135,
        "high": 1425,
        "low": 1405,
        "macd": -4.449268,
        "macd_hist": -12.918027,
        "macd_signal": 8.468759,
        "open": 1425,
        "rsi": 47.869819,
        "volume": 27427405,
        "zlsma": 1469.696181
      },
      {
        "close": 1440,
        "date": "2025-11-26",
        "ema20": 1433.072642,
        "ema200": 1198.376843,
        "ema5": 1418.070687,
        "ema60": 1373.293376,
        "high": 1440,
        "low": 1425,
        "macd": -2.926326,
        "macd_hist": -9.116068,
        "macd_signal": 6.189742,
        "open": 1430,
        "rsi": 51.672259,
        "volume": 29213211,
        "zlsma": 1464.730903
      },
      {
        "close": 1435,
        "date": "2025-11-27",
        "ema20": 1433.2562,
        "ema200": 1200.731302,
        "ema5": 1423.713792,
        "ema60": 1375.316544,
        "high": 1455,
        "low": 1430,
        "macd": -2.09865,
        "macd_hist": -6.630714,
        "macd_signal": 4.532064,
        "open": 1450,
        "rsi": 50.873022,
        "volume": 22039774,
        "zlsma": 1460.503472
      },
      {
        "close": 1440,
        "date": "2025-11-28",
        "ema20": 1433.898467,
        "ema200": 1203.112085,
        "ema5": 1429.142528,
        "ema60": 1377.437313,
        "high": 1455,
        "low": 1435,
        "macd": -1.02741,
        "macd_hist": -4.447579,
        "macd_signal": 3.420169,
        "open": 1440,
        "rsi": 51.677933,
        "volume": 23152513,
        "zlsma": 1454.635417
      },
      {
        "close": 1410,
        "date": "2025-12-01",
        "ema20": 1431.622422,
        "ema200": 1205.170671,
        "ema5": 1422.761685,
        "ema60": 1378.504942,
        "high": 1445,
        "low": 1410,
        "macd": -2.569573,
        "macd_hist": -4.791793,
        "macd_signal": 2.222221,
        "open": 1445,
        "rsi": 46.730661,
        "volume": 30559208,
        "zlsma": 1447.126736
      },
      {
        "close": 1430,
        "date": "2025-12-02",
        "ema20": 1431.467906,
        "ema200": 1207.407779,
        "ema5": 1425.174457,
        "ema60": 1380.193305,
        "high": 1440,
        "low": 1420,
        "macd": -2.153096,
        "macd_hist": -3.500253,
        "macd_signal": 1.347157,
        "open": 1430,
        "rsi": 50.156468,
        "volume": 23544477,
        "zlsma": 1439.331597
      },
      {
        "close": 1450,
        "date": "2025-12-03",
        "ema20": 1433.232867,
        "ema200": 1209.821632,
        "ema5": 1433.449638,
        "ema60": 1382.482049,
        "high": 1450,
        "low": 1435,
        "macd": -0.206818,
        "macd_hist": -1.24318,
        "macd_signal": 1.036362,
        "open": 1440,
        "rsi": 53.384937,
        "volume": 20301540,
        "zlsma": 1433.663194
      },
      {
        "close": 1445,
        "date": "2025-12-04",
        "ema20": 1434.353547,
        "ema200": 1212.161715,
        "ema5": 1437.299759,
        "ema60": 1384.531818,
        "high": 1450,
        "low": 1430,
        "macd": 0.921541,
        "macd_hist": -0.091857,
        "macd_signal": 1.013398,
        "open": 1445,
        "rsi": 52.469933,
        "volume": 20696944,
        "zlsma": 1428.368056
      },
      {
        "close": 1460,
        "date": "2025-12-05",
        "ema20": 1436.796066,
        "ema200": 1214.627768,
        "ema5": 1444.866506,
        "ema60": 1387.006185,
        "high": 1460,
        "low": 1440,
        "macd": 2.991661,
        "macd_hist": 1.582611,
        "macd_signal": 1.409051,
        "open": 1445,
        "rsi": 54.963793,
        "volume": 21072604,
        "zlsma": 1423.871528
      },
      {
        "close": 1495,
        "date": "2025-12-08",
        "ema20": 1442.339298,
        "ema200": 1217.417541,
        "ema5": 1461.57767,
        "ema60": 1390.546965,
        "high": 1495,
        "low": 1460,
        "macd": 7.371481,
        "macd_hist": 4.769944,
        "macd_signal": 2.601537,
        "open": 1465,
        "rsi": 60.209931,
        "volume": 24257260,
        "zlsma": 1423.046875
      },
      {
        "close": 1480,
        "date": "2025-12-09",
        "ema20": 1445.926031,
        "ema200": 1220.030302,
        "ema5": 1467.718447,
        "ema60": 1393.479852,
        "high": 1500,
        "low": 1480,
        "macd": 9.522376,
        "macd_hist": 5.536672,
        "macd_signal": 3.985705,
        "open": 1495,
        "rsi": 57.138004,
        "volume": 24235825,
        "zlsma": 1424.965278
      },
      {
        "close": 1505,
        "date": "2025-12-10",
        "ema20": 1451.552124,
        "ema200": 1222.865822,
        "ema5": 1480.145631,
        "ema60": 1397.13625,
        "high": 1505,
        "low": 1485,
        "macd": 13.093336,
        "macd_hist": 7.286105,
        "macd_signal": 5.807231,
        "open": 1490,
        "rsi": 60.7338,
        "volume": 23319221,
        "zlsma": 1428.758681
      },
      {
        "close": 1470,
        "date": "2025-12-11",
        "ema20": 1453.309064,
        "ema200": 1225.324868,
        "ema5": 1476.763754,
        "ema60": 1399.525225,
        "high": 1515,
        "low": 1465,
        "macd": 12.949861,
        "macd_hist": 5.714104,
        "macd_signal": 7.235757,
        "open": 1510,
        "rsi": 53.914484,
        "volume": 28924982,
        "zlsma": 1430.269097
      },
      {
        "close": 1480,
        "date": "2025-12-12",
        "ema20": 1455.851058,
        "ema200": 1227.858949,
        "ema5": 1477.842503,
        "ema60": 1402.163743,
        "high": 1485,
        "low": 1470,
        "macd": 13.487597,
        "macd_hist": 5.001472,
        "macd_signal": 8.486125,
        "open": 1475,
        "rsi": 55.453491,
        "volume": 22107664,
        "zlsma": 1431.545139
      },
      {
        "close": 1450,
        "date": "2025-12-15",
        "ema20": 1455.293814,
        "ema200": 1230.069308,
        "ema5": 1468.561669,
        "ema60": 1403.732145,
        "high": 1455,
        "low": 1445,
        "macd": 11.362032,
        "macd_hist": 2.300726,
        "macd_signal": 9.061306,
        "open": 1450,
        "rsi": 50.053235,
        "volume": 25889058,
        "zlsma": 1431.293403
      },
      {
        "close": 1435,
        "date": "2025-12-16",
        "ema20": 1453.36107,
        "ema200": 1232.108419,
        "ema5": 1457.374446,
        "ema60": 1404.75732,
        "high": 1445,
        "low": 1425,
        "macd": 8.370641,
        "macd_hist": -0.552532,
        "macd_signal": 8.923173,
        "open": 1435,
        "rsi": 47.559352,
        "volume": 32168064,
        "zlsma": 1429.097222
      },
      {
        "close": 1430,
        "date": "2025-12-17",
        "ema20": 1451.136206,
        "ema200": 1234.07749,
        "ema5": 1448.24963,
        "ema60": 1405.584949,
        "high": 1445,
        "low": 1425,
        "macd": 5.532706,
        "macd_hist": -2.712374,
        "macd_signal": 8.24508,
        "open": 1435,
        "rsi": 46.723664,
        "volume": 30535812,
        "zlsma": 1427.864583
      },
      {
        "close": 1430,
        "date": "2025-12-18",
        "ema20": 1449.123234,
        "ema200": 1236.026967,
        "ema5": 1442.16642,
        "ema60": 1406.385442,
        "high": 1435,
        "low": 1415,
        "macd": 3.246202,
        "macd_hist": -3.999102,
        "macd_signal": 7.245304,
        "open": 1420,
        "rsi": 46.723664,
        "volume": 30534136,
        "zlsma": 1429.114583
      },
      {
        "close": 1430,
        "date": "2025-12-19",
        "ema20": 1447.301974,
        "ema200": 1237.957047,
        "ema5": 1438.110947,
        "ema60": 1407.15969,
        "high": 1455,
        "low": 1430,
        "macd": 1.417787,
        "macd_hist": -4.662013,
        "macd_signal": 6.079801,
        "open": 1455,
        "rsi": 46.723664,
        "volume": 38763280,
        "zlsma": 1429.192708
      },
      {
        "close": 1465,
        "date": "2025-12-22",
        "ema20": 1448.9875,
        "ema200": 1240.216181,
        "ema5": 1447.073965,
        "ema60": 1409.056094,
        "high": 1470,
        "low": 1455,
        "macd": 2.761134,
        "macd_hist": -2.654933,
        "macd_signal": 5.416067,
        "open": 1465,
        "rsi": 53.818303,
        "volume": 22661665,
        "zlsma": 1435.381944
      },
      {
        "close": 1490,
        "date": "2025-12-23",
        "ema20": 1452.893453,
        "ema200": 1242.701592,
        "ema5": 1461.382643,
        "ema60": 1411.709992,
        "high": 1490,
        "low": 1470,
        "macd": 5.776451,
        "macd_hist": 0.288307,
        "macd_signal": 5.488144,
        "open": 1475,
        "rsi": 58.109407,
        "volume": 20739075,
        "zlsma": 1444.201389
      },
      {
        "close": 1495,
        "date": "2025-12-24",
        "ema20": 1456.9036,
        "ema200": 1245.212024,
        "ema5": 1472.588429,
        "ema60": 1414.440812,
        "high": 1500,
        "low": 1485,
        "macd": 8.47191,
        "macd_hist": 2.387012,
        "macd_signal": 6.084897,
        "open": 1495,
        "rsi": 58.931318,
        "volume": 12987261,
        "zlsma": 1448.315972
      },
      {
        "close": 1510,
        "date": "2025-12-26",
        "ema20": 1461.9604,
        "ema200": 1247.84673,
        "ema5": 1485.058952,
        "ema60": 1417.5739,
        "high": 1510,
        "low": 1495,
        "macd": 11.683772,
        "macd_hist": 4.4791,
        "macd_signal": 7.204672,
        "open": 1505,
        "rsi": 61.379438,
        "volume": 18823612,
        "zlsma": 1459.184028
      },
      {
        "close": 1530,
        "date": "2025-12-29",
        "ema20": 1468.440362,
        "ema200": 1250.654226,
        "ema5": 1500.039302,
        "ema60": 1421.260002,
        "high": 1530,
        "low": 1510,
        "macd": 15.662481,
        "macd_hist": 6.766247,
        "macd_signal": 8.896234,
        "open": 1515,
        "rsi": 64.424501,
        "volume": 21124648,
        "zlsma": 1472.100694
      },
      {
        "close": 1520,
        "date": "2025-12-30",
        "ema20": 1473.350804,
        "ema200": 1253.334283,
        "ema5": 1506.692868,
        "ema60": 1424.497379,
        "high": 1530,
        "low": 1510,
        "macd": 17.803493,
        "macd_hist": 7.125807,
        "macd_signal": 10.677686,
        "open": 1515,
        "rsi": 61.800729,
        "volume": 20325400,
        "zlsma": 1480.555556
      },
      {
        "close": 1550,
        "date": "2025-12-31",
        "ema20": 1480.650727,
        "ema200": 1256.286181,
        "ema5": 1521.128579,
        "ema60": 1428.612219,
        "high": 1550,
        "low": 1515,
        "macd": 21.671198,
        "macd_hist": 8.794809,
        "macd_signal": 12.876388,
        "open": 1520,
        "rsi": 66.242455,
        "volume": 29695967,
        "zlsma": 1489.201389
      },
      {
        "close": 1585,
        "date": "2026-01-02",
        "ema20": 1490.588753,
        "ema200": 1259.556965,
        "ema5": 1542.419052,
        "ema60": 1433.739687,
        "high": 1585,
        "low": 1545,
        "macd": 27.246508,
        "macd_hist": 11.496096,
        "macd_signal": 15.750412,
        "open": 1555,
        "rsi": 70.545534,
        "volume": 37512761,
        "zlsma": 1500.894097
      },
      {
        "close": 1670,
        "date": "2026-01-05",
        "ema20": 1507.675538,
        "ema200": 1263.640975,
        "ema5": 1584.946035,
        "ema60": 1441.485927,
        "high": 1695,
        "low": 1625,
        "macd": 38.084754,
        "macd_hist": 17.867473,
        "macd_signal": 20.21728,
        "open": 1630,
        "rsi": 77.909981,
        "volume": 66871820,
        "zlsma": 1518.784722
      },
      {
        "close": 1705,
        "date": "2026-01-06",
        "ema20": 1526.468344,
        "ema200": 1268.032607,
        "ema5": 1624.964023,
        "ema60": 1450.125733,
        "high": 1705,
        "low": 1645,
        "macd": 48.934266,
        "macd_hist": 22.973588,
        "macd_signal": 25.960678,
        "open": 1645,
        "rsi": 80.114707,
        "volume": 46751692,
        "zlsma": 1541.467014
      },
      {
        "close": 1675,
        "date": "2026-01-07",
        "ema20": 1540.614216,
        "ema200": 1272.082034,
        "ema5": 1641.642682,
        "ema60": 1457.49866,
        "high": 1685,
        "low": 1665,
        "macd": 54.483778,
        "macd_hist": 22.81848,
        "macd_signal": 31.665298,
        "open": 1665,
        "rsi": 73.356448,
        "volume": 49857449,
        "zlsma": 1559.427083
      },
      {
        "close": 1685,
        "date": "2026-01-08",
        "ema20": 1554.365243,
        "ema200": 1276.190671,
        "ema5": 1656.095121,
        "ema60": 1464.95772,
        "high": 1700,
        "low": 1655,
        "macd": 59.008509,
        "macd_hist": 21.874569,
        "macd_signal": 37.13394,
        "open": 1660,
        "rsi": 74.139557,
        "volume": 29215618,
        "zlsma": 1576.050347
      },
      {
        "close": 1680,
        "date": "2026-01-09",
        "ema20": 1566.330458,
        "ema200": 1280.208674,
        "ema5": 1664.063414,
        "ema60": 1472.008286,
        "high": 1700,
        "low": 1655,
        "macd": 61.482204,
        "macd_hist": 19.478611,
        "macd_signal": 42.003593,
        "open": 1665,
        "rsi": 72.984469,
        "volume": 37387656,
        "zlsma": 1592.170139
      },
      {
        "close": 1690,
        "date": "2026-01-12",
        "ema20": 1578.10851,
        "ema200": 1284.2862,
        "ema5": 1672.708943,
        "ema60": 1479.155556,
        "high": 1705,
        "low": 1690,
        "macd": 63.517353,
        "macd_hist": 17.211009,
        "macd_signal": 46.306345,
        "open": 1700,
        "rsi": 73.861589,
        "volume": 29987449,
        "zlsma": 1607.387153
      },
      {
        "close": 1710,
        "date": "2026-01-13",
        "ema20": 1590.669604,
        "ema200": 1288.522158,
        "ema5": 1685.139295,
        "ema60": 1486.724226,
        "high": 1720,
        "low": 1700,
        "macd": 65.983441,
        "macd_hist": 15.741677,
        "macd_signal": 50.241764,
        "open": 1720,
        "rsi": 75.569967,
        "volume": 30171800,
        "zlsma": 1620.963542
      },
      {
        "close": 1710,
        "date": "2026-01-14",
        "ema20": 1602.034404,
        "ema200": 1292.715967,
        "ema5": 1693.426197,
        "ema60": 1494.044743,
        "high": 1715,
        "low": 1700,
        "macd": 67.163612,
        "macd_hist": 13.537479,
        "macd_signal": 53.626134,
        "open": 1705,
        "rsi": 75.569967,
        "volume": 29100816,
        "zlsma": 1635.425347
      },
      {
        "close": 1690,
        "date": "2026-01-15",
        "ema20": 1610.41208,
        "ema200": 1296.669042,
        "ema5": 1692.284131,
        "ema60": 1500.469506,
        "high": 1700,
        "low": 1680,
        "macd": 65.727409,
        "macd_hist": 9.68102,
        "macd_signal": 56.046389,
        "open": 1685,
        "rsi": 70.24531,
        "volume": 36391886,
        "zlsma": 1645.885417
      },
      {
        "close": 1740,
        "date": "2026-01-16",
        "ema20": 1622.753786,
        "ema200": 1301.080295,
        "ema5": 1708.189421,
        "ema60": 1508.322965,
        "high": 1750,
        "low": 1710,
        "macd": 67.841753,
        "macd_hist": 9.436291,
        "macd_signal": 58.405461,
        "open": 1735,
        "rsi": 74.989752,
        "volume": 53551629,
        "zlsma": 1662.977431
      },
      {
        "close": 1760,
        "date": "2026-01-19",
        "ema20": 1635.824854,
        "ema200": 1305.646661,
        "ema5": 1725.459614,
        "ema60": 1516.574671,
        "high": 1780,
        "low": 1725,
        "macd": 70.320606,
        "macd_hist": 9.532115,
        "macd_signal": 60.78849,
        "open": 1725,
        "rsi": 76.597218,
        "volume": 29580038,
        "zlsma": 1680.425347
      },
      {
        "close": 1775,
        "date": "2026-01-20",
        "ema20": 1649.07963,
        "ema200": 1310.316843,
        "ema5": 1741.973076,
        "ema60": 1525.047632,
        "high": 1775,
        "low": 1740,
        "macd": 72.657934,
        "macd_hist": 9.495555,
        "macd_signal": 63.162379,
        "open": 1740,
        "rsi": 77.752153,
        "volume": 29401234,
        "zlsma": 1701.032986
      },
      {
        "close": 1740,
        "date": "2026-01-21",
        "ema20": 1657.738713,
        "ema200": 1314.592297,
        "ema5": 1741.315384,
        "ema60": 1532.095251,
        "high": 1765,
        "low": 1740,
        "macd": 70.86914,
        "macd_hist": 6.165409,
        "macd_signal": 64.703731,
        "open": 1745,
        "rsi": 69.173986,
        "volume": 45192749,
        "zlsma": 1719.375
      },
      {
        "close": 1760,
        "date": "2026-01-22",
        "ema20": 1667.477883,
        "ema200": 1319.024215,
        "ema5": 1747.543589,
        "ema60": 1539.567538,
        "high": 1770,
        "low": 1750,
        "macd": 70.25548,
        "macd_hist": 4.441399,
        "macd_signal": 65.814081,
        "open": 1765,
        "rsi": 71.133815,
        "volume": 32069478,
        "zlsma": 1739.175347
      },
      {
        "close": 1770,
        "date": "2026-01-23",
        "ema20": 1677.241894,
        "ema200": 1323.511536,
        "ema5": 1755.02906,
        "ema60": 1547.1227,
        "high": 1775,
        "low": 1750,
        "macd": 69.771781,
        "macd_hist": 3.16616,
        "macd_signal": 66.605621,
        "open": 1770,
        "rsi": 72.089304,
        "volume": 27601167,
        "zlsma": 1759.21875
      },
      {
        "close": 1755,
        "date": "2026-01-26",
        "ema20": 1684.647428,
        "ema200": 1327.804954,
        "ema5": 1755.019373,
        "ema60": 1553.93835,
        "high": 1785,
        "low": 1755,
        "macd": 67.401113,
        "macd_hist": 0.636393,
        "macd_signal": 66.764719,
        "open": 1765,
        "rsi": 68.430315,
        "volume": 22960198,
        "zlsma": 1777.421875
      },
      {
        "close": 1780,
        "date": "2026-01-27",
        "ema20": 1693.728625,
        "ema200": 1332.304407,
        "ema5": 1763.346249,
        "ema60": 1561.350207,
        "high": 1785,
        "low": 1755,
        "macd": 66.76995,
        "macd_hist": 0.004184,
        "macd_signal": 66.765765,
        "open": 1760,
        "rsi": 71.066215,
        "volume": 28985200,
        "zlsma": 1794.348958
      },
      {
        "close": 1820,
        "date": "2026-01-28",
        "ema20": 1705.754471,
        "ema200": 1337.157099,
        "ema5": 1782.230832,
        "ema60": 1569.830528,
        "high": 1820,
        "low": 1790,
        "macd": 68.705421,
        "macd_hist": 1.551725,
        "macd_signal": 67.153697,
        "open": 1790,
        "rsi": 74.705306,
        "volume": 29301156,
        "zlsma": 1812.118056
      },
      {
        "close": 1805,
        "date": "2026-01-29",
        "ema20": 1715.206426,
        "ema200": 1341.812253,
        "ema5": 1789.820555,
        "ema60": 1577.541003,
        "high": 1835,
        "low": 1800,
        "macd": 68.242267,
        "macd_hist": 0.870856,
        "macd_signal": 67.371411,
        "open": 1830,
        "rsi": 71.09422,
        "volume": 32224002,
        "zlsma": 1827.751736
      },
      {
        "close": 1775,
        "date": "2026-01-30",
        "ema20": 1720.901052,
        "ema200": 1346.122578,
        "ema5": 1784.88037,
        "ema60": 1584.015068,
        "high": 1800,
        "low": 1775,
        "macd": 64.708545,
        "macd_hist": -2.130293,
        "macd_signal": 66.838838,
        "open": 1790,
        "rsi": 64.390401,
        "volume": 40825139,
        "zlsma": 1839.392361
      },
      {
        "close": 1765,
        "date": "2026-02-02",
        "ema20": 1725.100952,
        "ema200": 1350.290513,
        "ema5": 1778.25358,
        "ema60": 1589.949,
        "high": 1765,
        "low": 1745,
        "macd": 60.404819,
        "macd_hist": -5.147215,
        "macd_signal": 65.552034,
        "open": 1750,
        "rsi": 62.282185,
        "volume": 28251381,
        "zlsma": 1848.394097
      },
      {
        "close": 1800,
        "date": "2026-02-03",
        "ema20": 1732.234194,
        "ema200": 1354.765234,
        "ema5": 1785.502387,
        "ema60": 1596.835918,
        "high": 1810,
        "low": 1785,
        "macd": 59.136603,
        "macd_hist": -5.132345,
        "macd_signal": 64.268948,
        "open": 1810,
        "rsi": 66.425571,
        "volume": 26744162,
        "zlsma": 1860.842014
      },
      {
        "close": 1785,
        "date": "2026-02-04",
        "ema20": 1737.259509,
        "ema200": 1359.046177,
        "ema5": 1785.334924,
        "ema60": 1603.005232,
        "high": 1805,
        "low": 1775,
        "macd": 56.272484,
        "macd_hist": -6.397171,
        "macd_signal": 62.669655,
        "open": 1785,
        "rsi": 63.22024,
        "volume": 26952301,
        "zlsma": 1869.322917
      },
      {
        "close": 1765,
        "date": "2026-02-05",
        "ema20": 1739.901461,
        "ema200": 1363.085519,
        "ema5": 1778.556616,
        "ema60": 1608.316536,
        "high": 1780,
        "low": 1760,
        "macd": 51.791792,
        "macd_hist": -8.70229,
        "macd_signal": 60.494082,
        "open": 1765,
        "rsi": 59.123652,
        "volume": 26299986,
        "zlsma": 1873.168403
      },
      {
        "close": 1780,
        "date": "2026-02-06",
        "ema20": 1743.720369,
        "ema200": 1367.233921,
        "ema5": 1779.037744,
        "ema60": 1613.945502,
        "high": 1780,
        "low": 1740,
        "macd": 48.88764,
        "macd_hist": -9.285154,
        "macd_signal": 58.172794,
        "open": 1745,
        "rsi": 61.156613,
        "volume": 33263592,
        "zlsma": 1871.388889
      },
      {
        "close": 1815,
        "date": "2026-02-09",
        "ema20": 1750.508906,
        "ema200": 1371.689305,
        "ema5": 1791.025163,
        "ema60": 1620.537453,
        "high": 1835,
        "low": 1815,
        "macd": 48.847206,
        "macd_hist": -7.46047,
        "macd_signal": 56.307677,
        "open": 1830,
        "rsi": 65.471738,
        "volume": 36529289,
        "zlsma": 1869.930556
      },
      {
        "close": 1880,
        "date": "2026-02-10",
        "ema20": 1762.841391,
        "ema200": 1376.747123,
        "ema5": 1820.683442,
        "ema60": 1629.044422,
        "high": 1880,
        "low": 1840,
        "macd": 53.444049,
        "macd_hist": -2.290902,
        "macd_signal": 55.734951,
        "open": 1845,
        "rsi": 71.748642,
        "volume": 41859169,
        "zlsma": 1876.458333
      },
      {
        "close": 1915,
        "date": "2026-02-11",
        "ema20": 1777.332687,
        "ema200": 1382.102873,
        "ema5": 1852.122295,
        "ema60": 1638.420015,
        "high": 1925,
        "low": 1875,
        "macd": 59.228538,
        "macd_hist": 2.79487,
        "macd_signal": 56.433668,
        "open": 1880,
        "rsi": 74.442803,
        "volume": 40488310,
        "zlsma": 1885.078125
      },
      {
        "close": 1900,
        "date": "2026-02-23",
        "ema20": 1789.015288,
        "ema200": 1387.256078,
        "ema5": 1868.08153,
        "ema60": 1646.996408,
        "high": 1935,
        "low": 1900,
        "macd": 61.888995,
        "macd_hist": 4.364261,
        "macd_signal": 57.524734,
        "open": 1900,
        "rsi": 71.304402,
        "volume": 69816209,
        "zlsma": 1892.890625
      },
      {
        "close": 1965,
        "date": "2026-02-24",
        "ema20": 1805.775737,
        "ema200": 1393.004774,
        "ema5": 1900.387686,
        "ema60": 1657.422755,
        "high": 1975,
        "low": 1915,
        "macd": 68.453295,
        "macd_hist": 8.742849,
        "macd_signal": 59.710446,
        "open": 1915,
        "rsi": 76.021859,
        "volume": 40961679,
        "zlsma": 1905.208333
      },
      {
        "close": 2015,
        "date": "2026-02-25",
        "ema20": 1825.701857,
        "ema200": 1399.193781,
        "ema5": 1938.591791,
        "ema60": 1669.146599,
        "high": 2025,
        "low": 1995,
        "macd": 76.804776,
        "macd_hist": 13.675464,
        "macd_signal": 63.129312,
        "open": 1995,
        "rsi": 78.895946,
        "volume": 40832607,
        "zlsma": 1919.869792
      },
      {
        "close": 1995,
        "date": "2026-02-26",
        "ema20": 1841.82549,
        "ema200": 1405.122201,
        "ema5": 1957.394527,
        "ema60": 1679.830317,
        "high": 2010,
        "low": 1995,
        "macd": 80.877248,
        "macd_hist": 14.198349,
        "macd_signal": 66.678899,
        "open": 2000,
        "rsi": 75.022304,
        "volume": 58561388,
        "zlsma": 1932.769097
      },
      {
        "close": 1975,
        "date": "2026-03-02",
        "ema20": 1854.508776,
        "ema200": 1410.792627,
        "ema5": 1963.263018,
        "ema60": 1689.508011,
        "high": 1995,
        "low": 1940,
        "macd": 81.550812,
        "macd_hist": 11.897531,
        "macd_signal": 69.653282,
        "open": 1940,
        "rsi": 71.254719,
        "volume": 48884884,
        "zlsma": 1945.494792
      },
      {
        "close": 1935,
        "date": "2026-03-03",
        "ema20": 1862.174607,
        "ema200": 1416.008621,
        "ema5": 1953.842012,
        "ema60": 1697.556929,
        "high": 1980,
        "low": 1935,
        "macd": 77.958297,
        "macd_hist": 6.644012,
        "macd_signal": 71.314285,
        "open": 1970,
        "rsi": 64.29973,
        "volume": 43090471,
        "zlsma": 1950.850694
      },
      {
        "close": 1865,
        "date": "2026-03-04",
        "ema20": 1862.443692,
        "ema200": 1420.476197,
        "ema5": 1924.228008,
        "ema60": 1703.046866,
        "high": 1910,
        "low": 1865,
        "macd": 68.671188,
        "macd_hist": -2.114477,
        "macd_signal": 70.785665,
        "open": 1895,
        "rsi": 54.309385,
        "volume": 68160943,
        "zlsma": 1949.010417
      },
      {
        "close": 1900,
        "date": "2026-03-05",
        "ema20": 1866.020484,
        "ema200": 1425.247578,
        "ema5": 1916.152005,
        "ema60": 1709.504346,
        "high": 1960,
        "low": 1895,
        "macd": 63.404409,
        "macd_hist": -5.905005,
        "macd_signal": 69.309414,
        "open": 1940,
        "rsi": 57.836823,
        "volume": 48120463,
        "zlsma": 1949.184028
      },
      {
        "close": 1890,
        "date": "2026-03-06",
        "ema20": 1868.304247,
        "ema200": 1429.87198,
        "ema5": 1907.43467,
        "ema60": 1715.422236,
        "high": 1900,
        "low": 1880,
        "macd": 57.757736,
        "macd_hist": -9.241342,
        "macd_signal": 66.999079,
        "open": 1880,
        "rsi": 56.494807,
        "volume": 30082724,
        "zlsma": 1951.710069
      },
      {
        "close": 1810,
        "date": "2026-03-09",
        "ema20": 1862.751462,
        "ema200": 1433.654349,
        "ema5": 1874.956447,
        "ema60": 1718.523146,
        "high": 1810,
        "low": 1770,
        "macd": 46.293731,
        "macd_hist": -16.564278,
        "macd_signal": 62.858009,
        "open": 1775,
        "rsi": 47.082659,
        "volume": 76459172,
        "zlsma": 1946.388889
      },
      {
        "close": 1850,
        "date": "2026-03-10",
        "ema20": 1861.537037,
        "ema200": 1437.797092,
        "ema5": 1866.637631,
        "ema60": 1722.833863,
        "high": 1890,
        "low": 1830,
        "macd": 39.97528,
        "macd_hist": -18.306183,
        "macd_signal": 58.281463,
        "open": 1870,
        "rsi": 51.439006,
        "volume": 41375691,
        "zlsma": 1944.019097
      },
      {
        "close": 1940,
        "date": "2026-03-11",
        "ema20": 1869.0097,
        "ema200": 1442.794135,
        "ema5": 1891.091754,
        "ema60": 1729.954064,
        "high": 1950,
        "low": 1875,
        "macd": 41.748855,
        "macd_hist": -13.226087,
        "macd_signal": 54.974942,
        "open": 1885,
        "rsi": 59.514842,
        "volume": 36167313,
        "zlsma": 1950.642361
      },
      {
        "close": 1885,
        "date": "2026-03-12",
        "ema20": 1870.532586,
        "ema200": 1447.194194,
        "ema5": 1889.061169,
        "ema60": 1735.037537,
        "high": 1915,
        "low": 1885,
        "macd": 38.275173,
        "macd_hist": -13.359815,
        "macd_signal": 51.634988,
        "open": 1900,
        "rsi": 53.643689,
        "volume": 34040589,
        "zlsma": 1950.963542
      },
      {
        "close": 1865,
        "date": "2026-03-13",
        "ema20": 1870.005673,
        "ema200": 1451.351465,
        "ema5": 1881.04078,
        "ema60": 1739.298602,
        "high": 1885,
        "low": 1840,
        "macd": 33.522002,
        "macd_hist": -14.490389,
        "macd_signal": 48.012391,
        "open": 1840,
        "rsi": 51.648395,
        "volume": 31214304,
        "zlsma": 1946.779514
      },
      {
        "close": 1845,
        "date": "2026-03-16",
        "ema20": 1867.62418,
        "ema200": 1455.268366,
        "ema5": 1869.027186,
        "ema60": 1742.764221,
        "high": 1880,
        "low": 1845,
        "macd": 27.820548,
        "macd_hist": -16.153474,
        "macd_signal": 43.974022,
        "open": 1875,
        "rsi": 49.65922,
        "volume": 31249086,
        "zlsma": 1942.647569
      },
      {
        "close": 1870,
        "date": "2026-03-17",
        "ema20": 1867.850449,
        "ema200": 1459.395049,
        "ema5": 1869.351458,
        "ema60": 1746.935886,
        "high": 1880,
        "low": 1860,
        "macd": 25.030856,
        "macd_hist": -15.154533,
        "macd_signal": 40.185389,
        "open": 1875,
        "rsi": 52.140517,
        "volume": 23812211,
        "zlsma": 1943.394097
      },
      {
        "close": 1905,
        "date": "2026-03-18",
        "ema20": 1871.388501,
        "ema200": 1463.828929,
        "ema5": 1881.234305,
        "ema60": 1752.118316,
        "high": 1910,
        "low": 1890,
        "macd": 25.351971,
        "macd_hist": -11.866734,
        "macd_signal": 37.218705,
        "open": 1900,
        "rsi": 55.451129,
        "volume": 23068156,
        "zlsma": 1948.055556
      },
      {
        "close": 1850,
        "date": "2026-03-19",
        "ema20": 1869.351501,
        "ema200": 1467.671428,
        "ema5": 1870.82287,
        "ema60": 1755.327552,
        "high": 1880,
        "low": 1850,
        "macd": 20.927181,
        "macd_hist": -13.03322,
        "macd_signal": 33.9604,
        "open": 1875,
        "rsi": 49.64011,
        "volume": 31040569,
        "zlsma": 1945.616319
      },
      {
        "close": 1840,
        "date": "2026-03-20",
        "ema20": 1866.55612,
        "ema200": 1471.376189,
        "ema5": 1860.54858,
        "ema60": 1758.103698,
        "high": 1870,
        "low": 1840,
        "macd": 16.424258,
        "macd_hist": -14.028914,
        "macd_signal": 30.453172,
        "open": 1860,
        "rsi": 48.642007,
        "volume": 46312322,
        "zlsma": 1943.90625
      },
      {
        "close": 1810,
        "date": "2026-03-23",
        "ema20": 1861.169823,
        "ema200": 1474.745581,
        "ema5": 1843.699053,
        "ema60": 1759.805216,
        "high": 1815,
        "low": 1785,
        "macd": 10.315993,
        "macd_hist": -16.109743,
        "macd_signal": 26.425736,
        "open": 1790,
        "rsi": 45.674945,
        "volume": 34902948,
        "zlsma": 1941.597222
      },
      {
        "close": 1810,
        "date": "2026-03-24",
        "ema20": 1856.296506,
        "ema200": 1478.081445,
        "ema5": 1832.466036,
        "ema60": 1761.450946,
        "high": 1850,
        "low": 1800,
        "macd": 5.412755,
        "macd_hist": -16.810385,
        "macd_signal": 22.22314,
        "open": 1850,
        "rsi": 45.674945,
        "volume": 27001025,
        "zlsma": 1938.177083
      },
      {
        "close": 1845,
        "date": "2026-03-25",
        "ema20": 1855.220649,
        "ema200": 1481.732376,
        "ema5": 1836.644024,
        "ema60": 1764.19026,
        "high": 1875,
        "low": 1845,
        "macd": 4.301525,
        "macd_hist": -14.337292,
        "macd_signal": 18.638817,
        "open": 1865,
        "rsi": 49.816753,
        "volume": 40964040,
        "zlsma": 1934.895833
      },
      {
        "close": 1840,
        "date": "2026-03-26",
        "ema20": 1853.771063,
        "ema200": 1485.297228,
        "ema5": 1837.762682,
        "ema60": 1766.675825,
        "high": 1865,
        "low": 1840,
        "macd": 2.983023,
        "macd_hist": -12.524635,
        "macd_signal": 15.507658,
        "open": 1850,
        "rsi": 49.239206,
        "volume": 20958470,
        "zlsma": 1926.206597
      },
      {
        "close": 1820,
        "date": "2026-03-27",
        "ema20": 1850.554771,
        "ema200": 1488.627604,
        "ema5": 1831.841788,
        "ema60": 1768.424158,
        "high": 1825,
        "low": 1800,
        "macd": 0.320572,
        "macd_hist": -12.149669,
        "macd_signal": 12.470241,
        "open": 1805,
        "rsi": 46.897119,
        "volume": 28974140,
        "zlsma": 1913.498264
      },
      {
        "close": 1780,
        "date": "2026-03-30",
        "ema20": 1843.835269,
        "ema200": 1491.526832,
        "ema5": 1814.561192,
        "ema60": 1768.803694,
        "high": 1800,
        "low": 1780,
        "macd": -4.95993,
        "macd_hist": -13.944137,
        "macd_signal": 8.984207,
        "open": 1780,
        "rsi": 42.539048,
        "volume": 39889700,
        "zlsma": 1899.296875
      },
      {
        "close": 1760,
        "date": "2026-03-31",
        "ema20": 1835.850958,
        "ema200": 1494.198207,
        "ema5": 1796.374128,
        "ema60": 1768.515048,
        "high": 1790,
        "low": 1760,
        "macd": -10.635994,
        "macd_hist": -15.69616,
        "macd_signal": 5.060167,
        "open": 1775,
        "rsi": 40.511899,
        "volume": 49221091,
        "zlsma": 1878.845486
      },
      {
        "close": 1855,
        "date": "2026-04-01",
        "ema20": 1837.674676,
        "ema200": 1497.788274,
        "ema5": 1815.916085,
        "ema60": 1771.350621,
        "high": 1855,
        "low": 1830,
        "macd": -7.383497,
        "macd_hist": -9.954931,
        "macd_signal": 2.571434,
        "open": 1840,
        "rsi": 52.171049,
        "volume": 35537379,
        "zlsma": 1862.951389
      },
      {
        "close": 1810,
        "date": "2026-04-02",
        "ema20": 1835.038993,
        "ema200": 1500.894859,
        "ema5": 1813.944057,
        "ema60": 1772.617813,
        "high": 1865,
        "low": 1805,
        "macd": -8.340845,
        "macd_hist": -8.729823,
        "macd_signal": 0.388978,
        "open": 1865,
        "rsi": 47.429116,
        "volume": 25132417,
        "zlsma": 1845.789931
      },
      {
        "close": 1860,
        "date": "2026-04-07",
        "ema20": 1837.416232,
        "ema200": 1504.468044,
        "ema5": 1829.296038,
        "ema60": 1775.482803,
        "high": 1860,
        "low": 1835,
        "macd": -5.007248,
        "macd_hist": -4.316981,
        "macd_signal": -0.690267,
        "open": 1850,
        "rsi": 52.585864,
        "volume": 17953562,
        "zlsma": 1835.15625
      },
      {
        "close": 1950,
        "date": "2026-04-08",
        "ema20": 1848.138495,
        "ema200": 1508.901198,
        "ema5": 1869.530692,
        "ema60": 1781.204678,
        "high": 1950,
        "low": 1925,
        "macd": 4.841094,
        "macd_hist": 4.425089,
        "macd_signal": 0.416005,
        "open": 1935,
        "rsi": 60.161084,
        "volume": 46515921,
        "zlsma": 1835.668403
      },
      {
        "close": 1955,
        "date": "2026-04-09",
        "ema20": 1858.315781,
        "ema200": 1513.339992,
        "ema5": 1898.020461,
        "ema60": 1786.902886,
        "high": 1955,
        "low": 1930,
        "macd": 12.900723,
        "macd_hist": 9.987774,
        "macd_signal": 2.912949,
        "open": 1945,
        "rsi": 60.538288,
        "volume": 31835073,
        "zlsma": 1842.456597
      },
      {
        "close": 2000,
        "date": "2026-04-10",
        "ema20": 1871.809516,
        "ema200": 1518.18238,
        "ema5": 1932.013641,
        "ema60": 1793.889676,
        "high": 2000,
        "low": 1970,
        "macd": 22.657974,
        "macd_hist": 15.79602,
        "macd_signal": 6.861954,
        "open": 1975,
        "rsi": 63.855249,
        "volume": 28637625,
        "zlsma": 1850.121528
      },
      {
        "close": 1990,
        "date": "2026-04-13",
        "ema20": 1883.065753,
        "ema200": 1522.877083,
        "ema5": 1951.342427,
        "ema60": 1800.319523,
        "high": 1995,
        "low": 1975,
        "macd": 29.246612,
        "macd_hist": 17.907727,
        "macd_signal": 11.338885,
        "open": 1985,
        "rsi": 62.596081,
        "volume": 28968757,
        "zlsma": 1857.873264
      },
      {
        "close": 2055,
        "date": "2026-04-14",
        "ema20": 1899.440443,
        "ema200": 1528.171838,
        "ema5": 1985.894952,
        "ema60": 1808.669703,
        "high": 2055,
        "low": 2010,
        "macd": 39.260542,
        "macd_hist": 22.337325,
        "macd_signal": 16.923217,
        "open": 2015,
        "rsi": 67.132856,
        "volume": 39113405,
        "zlsma": 1877.369792
      },
      {
        "close": 2080,
        "date": "2026-04-15",
        "ema20": 1916.636591,
        "ema200": 1533.662666,
        "ema5": 2017.263301,
        "ema60": 1817.565778,
        "high": 2100,
        "low": 2060,
        "macd": 48.653101,
        "macd_hist": 25.383907,
        "macd_signal": 23.269194,
        "open": 2065,
        "rsi": 68.705083,
        "volume": 40343568,
        "zlsma": 1895.355903
      },
      {
        "close": 2085,
        "date": "2026-04-16",
        "ema20": 1932.671202,
        "ema200": 1539.148609,
        "ema5": 2039.842201,
        "ema60": 1826.334113,
        "high": 2090,
        "low": 2055,
        "macd": 55.856353,
        "macd_hist": 26.069728,
        "macd_signal": 29.786625,
        "open": 2080,
        "rsi": 69.02423,
        "volume": 32038524,
        "zlsma": 1906.328125
      },
      {
        "close": 2030,
        "date": "2026-04-17",
        "ema20": 1941.940611,
        "ema200": 1544.032703,
        "ema5": 2036.561467,
        "ema60": 1833.011683,
        "high": 2060,
        "low": 2030,
        "macd": 56.475922,
        "macd_hist": 21.351438,
        "macd_signal": 35.124485,
        "open": 2055,
        "rsi": 61.584379,
        "volume": 39260244,
        "zlsma": 1917.230903
      },
      {
        "close": 2025,
        "date": "2026-04-20",
        "ema20": 1949.851029,
        "ema200": 1548.818447,
        "ema5": 2032.707645,
        "ema60": 1839.306382,
        "high": 2055,
        "low": 2025,
        "macd": 55.918879,
        "macd_hist": 16.635516,
        "macd_signal": 39.283364,
        "open": 2030,
        "rsi": 60.941297,
        "volume": 25407621,
        "zlsma": 1929.184028
      },
      {
        "close": 2050,
        "date": "2026-04-21",
        "ema20": 1959.389026,
        "ema200": 1553.805328,
        "ema5": 2038.471763,
        "ema60": 1846.21437,
        "high": 2075,
        "low": 2045,
        "macd": 56.8395,
        "macd_hist": 14.044909,
        "macd_signal": 42.794591,
        "open": 2050,
        "rsi": 63.020566,
        "volume": 25783476,
        "zlsma": 1944.600694
      },
      {
        "close": 2050,
        "date": "2026-04-22",
        "ema20": 1968.018643,
        "ema200": 1558.742589,
        "ema5": 2042.314509,
        "ema60": 1852.895866,
        "high": 2070,
        "low": 2040,
        "macd": 56.91304,
        "macd_hist": 11.294759,
        "macd_signal": 45.618281,
        "open": 2045,
        "rsi": 63.020566,
        "volume": 24762881,
        "zlsma": 1957.786458
      },
      {
        "close": 2080,
        "date": "2026-04-23",
        "ema20": 1978.683534,
        "ema200": 1563.929229,
        "ema5": 2054.876339,
        "ema60": 1860.341903,
        "high": 2135,
        "low": 2055,
        "macd": 58.715237,
        "macd_hist": 10.477565,
        "macd_signal": 48.237672,
        "open": 2090,
        "rsi": 65.571294,
        "volume": 48682193,
        "zlsma": 1970.494792
      },
      {
        "close": 2185,
        "date": "2026-04-24",
        "ema20": 1998.332721,
        "ema200": 1570.109038,
        "ema5": 2098.250893,
        "ema60": 1870.986431,
        "high": 2190,
        "low": 2105,
        "macd": 67.834164,
        "macd_hist": 15.677194,
        "macd_signal": 52.15697,
        "open": 2110,
        "rsi": 72.675414,
        "volume": 45088050,
        "zlsma": 1996.041667
      },
      {
        "close": 2265,
        "date": "2026-04-27",
        "ema20": 2023.729605,
        "ema200": 1577.023376,
        "ema5": 2153.833929,
        "ema60": 1883.904908,
        "high": 2330,
        "low": 2265,
        "macd": 80.58735,
        "macd_hist": 22.744304,
        "macd_signal": 57.843046,
        "open": 2280,
        "rsi": 76.631812,
        "volume": 68696037,
        "zlsma": 2028.446181
      },
      {
        "close": 2215,
        "date": "2026-04-28",
        "ema20": 2041.945833,
        "ema200": 1583.371402,
        "ema5": 2174.222619,
        "ema60": 1894.760485,
        "high": 2280,
        "low": 2215,
        "macd": 85.672184,
        "macd_hist": 22.26331,
        "macd_signal": 63.408874,
        "open": 2245,
        "rsi": 69.826738,
        "volume": 47175356,
        "zlsma": 2058.559028
      },
      {
        "close": 2180,
        "date": "2026-04-29",
        "ema20": 2055.093849,
        "ema200": 1589.308005,
        "ema5": 2176.148413,
        "ema60": 1904.1126,
        "high": 2210,
        "low": 2165,
        "macd": 85.887684,
        "macd_hist": 17.983048,
        "macd_signal": 67.904636,
        "open": 2175,
        "rsi": 65.4456,
        "volume": 42895935,
        "zlsma": 2085.164931
      },
      {
        "close": 2135,
        "date": "2026-04-30",
        "ema20": 2062.703959,
        "ema200": 1594.737776,
        "ema5": 2162.432275,
        "ema60": 1911.682679,
        "high": 2215,
        "low": 2135,
        "macd": 81.488003,
        "macd_hist": 10.866694,
        "macd_signal": 70.621309,
        "open": 2205,
        "rsi": 60.214474,
        "volume": 48975164,
        "zlsma": 2104.652778
      },
      {
        "close": 2275,
        "date": "2026-05-04",
        "ema20": 2082.922629,
        "ema200": 1601.506555,
        "ema5": 2199.95485,
        "ema60": 1923.594722,
        "high": 2285,
        "low": 2195,
        "macd": 88.280412,
        "macd_hist": 14.127282,
        "macd_signal": 74.15313,
        "open": 2200,
        "rsi": 68.618519,
        "volume": 38390062,
        "zlsma": 2135.399306
      },
      {
        "close": 2250,
        "date": "2026-05-05",
        "ema20": 2098.83476,
        "ema200": 1607.959226,
        "ema5": 2216.636567,
        "ema60": 1934.296535,
        "high": 2270,
        "low": 2240,
        "macd": 90.601754,
        "macd_hist": 13.158899,
        "macd_signal": 77.442855,
        "open": 2250,
        "rsi": 65.939916,
        "volume": 21625279,
        "zlsma": 2164.817708
      },
      {
        "close": 2250,
        "date": "2026-05-06",
        "ema20": 2113.231449,
        "ema200": 1614.347691,
        "ema5": 2227.757711,
        "ema60": 1944.647468,
        "high": 2285,
        "low": 2240,
        "macd": 91.38797,
        "macd_hist": 11.156092,
        "macd_signal": 80.231878,
        "open": 2250,
        "rsi": 65.939916,
        "volume": 31918664,
        "zlsma": 2196.545139
      },
      {
        "close": 2310,
        "date": "2026-05-07",
        "ema20": 2131.971311,
        "ema200": 1621.269605,
        "ema5": 2255.171807,
        "ema60": 1956.626239,
        "high": 2345,
        "low": 2310,
        "macd": 95.748818,
        "macd_hist": 12.413552,
        "macd_signal": 83.335266,
        "open": 2335,
        "rsi": 69.277999,
        "volume": 35034517,
        "zlsma": 2233.628472
      },
      {
        "close": 2290,
        "date": "2026-05-08",
        "ema20": 2147.021663,
        "ema200": 1627.923638,
        "ema5": 2266.781205,
        "ema60": 1967.556527,
        "high": 2310,
        "low": 2265,
        "macd": 96.47884,
        "macd_hist": 10.51486,
        "macd_signal": 85.963981,
        "open": 2300,
        "rsi": 66.923527,
        "volume": 27102571,
        "zlsma": 2260.095486
      },
      {
        "close": 2235,
        "date": "2026-05-11",
        "ema20": 2155.400552,
        "ema200": 1633.964199,
        "ema5": 2256.18747,
        "ema60": 1976.325165,
        "high": 2275,
        "low": 2235,
        "macd": 91.563857,
        "macd_hist": 4.479901,
        "macd_signal": 87.083956,
        "open": 2265,
        "rsi": 60.803616,
        "volume": 37244077,
        "zlsma": 2284.670139
      },
      {
        "close": 2255,
        "date": "2026-05-12",
        "ema20": 2164.886214,
        "ema200": 1640.14366,
        "ema5": 2255.791647,
        "ema60": 1985.462045,
        "high": 2280,
        "low": 2210,
        "macd": 88.265065,
        "macd_hist": 0.944887,
        "macd_signal": 87.320178,
        "open": 2235,
        "rsi": 62.158754,
        "volume": 44459541,
        "zlsma": 2305.859375
      },
      {
        "close": 2220,
        "date": "2026-05-13",
        "ema20": 2170.135146,
        "ema200": 1645.913375,
        "ema5": 2243.861098,
        "ema60": 1993.151814,
        "high": 2240,
        "low": 2205,
        "macd": 81.882649,
        "macd_hist": -4.350023,
        "macd_signal": 86.232672,
        "open": 2205,
        "rsi": 58.35643,
        "volume": 35350292,
        "zlsma": 2316.189236
      },
      {
        "close": 2270,
        "date": "2026-05-14",
        "ema20": 2179.646084,
        "ema200": 1652.123192,
        "ema5": 2252.574065,
        "ema60": 2002.228804,
        "high": 2270,
        "low": 2230,
        "macd": 79.937649,
        "macd_hist": -5.036018,
        "macd_signal": 84.973667,
        "open": 2250,
        "rsi": 61.938389,
        "volume": 31747100,
        "zlsma": 2329.878472
      },
      {
        "close": 2265,
        "date": "2026-05-15",
        "ema20": 2187.775029,
        "ema200": 1658.221469,
        "ema5": 2256.716043,
        "ema60": 2010.844253,
        "high": 2325,
        "low": 2250,
        "macd": 77.103958,
        "macd_hist": -6.295767,
        "macd_signal": 83.399726,
        "open": 2310,
        "rsi": 61.369912,
        "volume": 29922154,
        "zlsma": 2339.114583
      },
      {
        "close": 2240,
        "date": "2026-05-18",
        "ema20": 2192.748835,
        "ema200": 1664.01031,
        "ema5": 2251.144029,
        "ema60": 2018.357556,
        "high": 2260,
        "low": 2215,
        "macd": 72.01085,
        "macd_hist": -9.1111,
        "macd_signal": 81.121951,
        "open": 2225,
        "rsi": 58.479808,
        "volume": 25875079,
        "zlsma": 2346.840278
      },
      {
        "close": 2205,
        "date": "2026-05-19",
        "ema20": 2193.915613,
        "ema200": 1669.393292,
        "ema5": 2235.762686,
        "ema60": 2024.47698,
        "high": 2230,
        "low": 2205,
        "macd": 64.407864,
        "macd_hist": -13.371269,
        "macd_signal": 77.779133,
        "open": 2220,
        "rsi": 54.602891,
        "volume": 34824449,
        "zlsma": 2346.397569
      },
      {
        "close": 2185,
        "date": "2026-05-20",
        "ema20": 2193.066507,
        "ema200": 1674.523707,
        "ema5": 2218.841791,
        "ema60": 2029.74003,
        "high": 2210,
        "low": 2185,
        "macd": 56.121675,
        "macd_hist": -17.325967,
        "macd_signal": 73.447642,
        "open": 2205,
        "rsi": 52.462581,
        "volume": 29320253,
        "zlsma": 2342.421875
      },
      {
        "close": 2230,
        "date": "2026-05-21",
        "ema20": 2196.583982,
        "ema200": 1680.050834,
        "ema5": 2222.561194,
        "ema60": 2036.305931,
        "high": 2255,
        "low": 2230,
        "macd": 52.579826,
        "macd_hist": -16.694252,
        "macd_signal": 69.274079,
        "open": 2240,
        "rsi": 56.586006,
        "volume": 22964974,
        "zlsma": 2341.779514
      },
      {
        "close": 2255,
        "date": "2026-05-22",
        "ema20": 2202.147413,
        "ema200": 1685.771721,
        "ema5": 2233.374129,
        "ema60": 2043.476228,
        "high": 2260,
        "low": 2225,
        "macd": 51.199975,
        "macd_hist": -14.459283,
        "macd_signal": 65.659258,
        "open": 2245,
        "rsi": 58.727868,
        "volume": 26171751,
        "zlsma": 2347.664931
      }
    ],
    "status": "ok",
    "symbol": "2330.TW"
  },
  "title": "2330 — 台積電",
  "tradingHtml": "<h1>2330.TW — 多角色股票分析（2026-05-22）</h1>\n<p><strong>投資期間：</strong> 中期（1-6 個月） · <strong>分析深度：</strong> standard</p>\n<h2>最終建議</h2>\n<ul>\n<li><strong>操作傾向：</strong> HOLD（續抱 / 觀望）</li>\n<li><strong>信心程度：</strong> MEDIUM（中）</li>\n<li><strong>風險結論：</strong> APPROVED WITH ADJUSTMENT（調整後通過）</li>\n<li><strong>進場確認條件：</strong> 觀望轉偏多需看到收盤重新站上 NT$2,310-2,345 區間且成交量高於 20 日均量，或後續月營收與 Q2 實績持續貼近公司 US$39.0-40.2B 營收指引與 65.5%-67.5% 毛利率指引（來源：<a href=\"https://investor.tsmc.com/english/quarterly-results/2026/q1\" rel=\"noopener noreferrer\" target=\"_blank\">TSMC Q1 2026 results</a>、<a href=\"https://www.twse.com.tw/exchangeReport/STOCK_DAY?response=json&amp;date=20260501&amp;stockNo=2330\" rel=\"noopener noreferrer\" target=\"_blank\">TWSE 2330 2026/05 股價資料</a>）</li>\n<li><strong>失效條件：</strong> 若跌破 NT$2,185 後無法收復、再失守 60 日均線約 NT$2,018，或公司下修 2026 年美元營收成長「above 30%」展望，則中期多方 thesis 失效（來源：<a href=\"https://investor.tsmc.com/english/encrypt/files/encrypt_file/reports/2026-04/3cef85204275f94fd111485cfdf4adb3c0263c45/TSMC%201Q26%20Transcript.pdf\" rel=\"noopener noreferrer\" target=\"_blank\">TSMC 1Q26 transcript</a>）</li>\n</ul>\n<h2>分析師發現</h2>\n<h3>基本面</h3>\n<ul>\n<li>1Q26 營收 NT$1,134.10B、年增 35.1%；淨利 NT$572.48B、EPS NT$22.08、年增 58.3%；毛利率 66.2%、營益率 58.1%，顯示 AI / 先進製程需求仍強（來源：<a href=\"https://investor.tsmc.com/english/encrypt/files/encrypt_file/qr/phase4_reports/2026-04/bd8eb0403902fdea59a2f5e390e48d010b50edc9/1Q26%20EarningsRelease_WoG.pdf\" rel=\"noopener noreferrer\" target=\"_blank\">TSMC earnings release</a>）。</li>\n<li>1Q26 HPC 佔營收 61%，3nm / 5nm / 7nm 合計先進製程佔晶圓營收 74%；北美客戶佔 76%，成長集中度高但地緣與客戶集中風險也高（來源：<a href=\"https://investor.tsmc.com/english/encrypt/files/encrypt_file/reports/2026-04/5508a9df8981f587c73dbfaf9f577f142e22bbb1/1Q26ManagementReport.pdf\" rel=\"noopener noreferrer\" target=\"_blank\">TSMC management report</a>）。</li>\n<li>資產負債表強：1Q26 現金與有價證券 NT$3.38T、長期有息負債 NT$901.02B、流動比率 2.5x；1Q26 FCF 約 NT$348.21B（來源：<a href=\"https://investor.tsmc.com/english/encrypt/files/encrypt_file/reports/2026-04/a7e3abe65a3fbc342aa55f9f53a5490dd621c1ac/1Q26%20Presentation%20%28E%29.pdf\" rel=\"noopener noreferrer\" target=\"_blank\">TSMC presentation</a>）。</li>\n<li>估值不便宜但尚非最極端：以 2026-05-21 收盤 NT$2,230 與 FactSet 2026 EPS 中位數 NT$93.01 推算，forward P/E 約 24.0x；TSM ADR forward P/E 約 21.44x，低於 ASML 39.72x、接近 NVDA 22.08x（來源：<a href=\"https://www.twse.com.tw/exchangeReport/STOCK_DAY?response=json&amp;date=20260501&amp;stockNo=2330\" rel=\"noopener noreferrer\" target=\"_blank\">TWSE</a>、<a href=\"https://news.cnyes.com/news/id/6422450\" rel=\"noopener noreferrer\" target=\"_blank\">Cnyes FactSet</a>、<a href=\"https://stockanalysis.com/stocks/tsm/\" rel=\"noopener noreferrer\" target=\"_blank\">TSM StockAnalysis</a>、<a href=\"https://stockanalysis.com/stocks/nvda/financials/ratios/\" rel=\"noopener noreferrer\" target=\"_blank\">NVDA ratios</a>、<a href=\"https://stockanalysis.com/stocks/asml/\" rel=\"noopener noreferrer\" target=\"_blank\">ASML</a>）。</li>\n</ul>\n<h3>情緒面</h3>\n<ul>\n<li>法人預估偏多：FactSet 45 位分析師將 2026 EPS 中位數由 NT$91.77 上修至 NT$93.01，目標價 NT$2,387.5（來源：<a href=\"https://news.cnyes.com/news/id/6422450\" rel=\"noopener noreferrer\" target=\"_blank\">Cnyes FactSet</a>）。</li>\n<li>2026-05-21 三大法人合計買超 1,604,835 股，其中外資買超 1,014,338 股、投信買超 167,000 股，短線籌碼由前段回檔轉為小幅修復（來源：<a href=\"https://www.twse.com.tw/fund/T86?response=json&amp;date=20260521&amp;selectType=ALLBUT0999\" rel=\"noopener noreferrer\" target=\"_blank\">TWSE T86</a>）。</li>\n<li>期權活動偏熱但方向不明：Futu 顯示 5/21 台積電期權成交 14.05 萬張、未平倉 179.33 萬張；未取得可驗證 put/call ratio，因此不判定單向看多或看空（來源：<a href=\"https://news.futunn.com/hk/post/73483306?futusource=news_search_searchnews&amp;src=39\" rel=\"noopener noreferrer\" target=\"_blank\">Futu news</a>）。</li>\n<li>散戶社群量化情緒：unavailable；可驗證公開資料不足。信用交易上，2026-05-21 融資餘額 26,952 張、融券餘額 100 張，未見高融券壓力（來源：<a href=\"https://www.twse.com.tw/exchangeReport/MI_MARGN?response=json&amp;date=20260521&amp;selectType=ALL\" rel=\"noopener noreferrer\" target=\"_blank\">TWSE MI_MARGN</a>）。</li>\n</ul>\n<h3>新聞（過去 30 天）</h3>\n<ul>\n<li>AMD Announces Production Ramp of Next-Generation AMD EPYC Processor “Venice” on TSMC 2nm Process Technology — 2026-05-21 — https://www.amd.com/en/newsroom/press-releases/2026-5-20-amd-announces-production-ramp-of-next-generation-a.html</li>\n<li>AMD Announces More Than $10 Billion in Taiwan Ecosystem Investments to Accelerate AI Infrastructure — 2026-05-21 — https://www.amd.com/en/newsroom/press-releases/2026-5-20-amd-announces-more-than-10-billion-in-taiwan-ecos.html</li>\n<li>NVIDIA Announces Financial Results for First Quarter Fiscal 2027，Data Center revenue $75.2B、年增 92%，networking revenue $14.8B、年增 199% — 2026-05-20 — https://nvidianews.nvidia.com/news/nvidia-announces-financial-results-for-first-quarter-fiscal-2027</li>\n<li>TSMC touts advanced packaging, 2nm progress at tech symposium；5.5-reticle CoWoS yield 超過 98% — 2026-05-14 — https://focustaiwan.tw/sci-tech/202605140021</li>\n<li>AI to drive semiconductor growth to US$1.5 trillion by 2030: TSMC；AI/HPC 預期佔 2030 半導體市場 55% — 2026-05-14 — https://focustaiwan.tw/sci-tech/202605140009</li>\n<li>TSMC April 2026 Revenue Report；4 月營收 NT$410.73B、年增 17.5%，1-4 月累計 NT$1,544.83B、年增 29.9% — 2026-05-08 — https://pr.tsmc.com/english/news/3305</li>\n<li>TSMC Debuts A13 Technology at 2026 North America Technology Symposium；N16HV 支援近眼顯示、智慧眼鏡等邊緣 AI 應用 — 2026-04-23 — https://pr.tsmc.com/english/news/3302</li>\n<li>Taiwan declares itself sovereign and independent after Trump questions US defense commitment；地緣政治風險升溫 — 2026-05-17 — https://www.tomshardware.com/tech-industry/taiwan-declares-itself-sovreign-and-independent-after-trump-questions-us-defense-commitment</li>\n</ul>\n<h3>技術面</h3>\n<ul>\n<li>截至可取得的最近收盤 2026-05-21，2330.TW 收 NT$2,230，當日量 24.93M 股，低於 20 日均量約 44.79M 股；反彈量能尚未確認突破（來源：<a href=\"https://www.twse.com.tw/exchangeReport/STOCK_DAY?response=json&amp;date=20260501&amp;stockNo=2330\" rel=\"noopener noreferrer\" target=\"_blank\">TWSE STOCK_DAY</a>）。</li>\n<li>股價高於 5 日均線 NT$2,225、20 日均線 NT$2,227、60 日均線 NT$2,018、120 日均線 NT$1,808，主趨勢仍偏多；但低於 10 日均線 NT$2,239，短線仍在整理（來源：依 TWSE 月資料自行計算，<a href=\"https://www.twse.com.tw/exchangeReport/STOCK_DAY?response=json&amp;date=20260501&amp;stockNo=2330\" rel=\"noopener noreferrer\" target=\"_blank\">最新月資料</a>）。</li>\n<li>RSI(14) 約 56.6，屬中性偏強；MACD 仍高於零但低於 signal，histogram 約 -16.7，代表上升趨勢中的動能降溫（來源：依 TWSE 日資料自行計算，<a href=\"https://www.twse.com.tw/exchangeReport/STOCK_DAY?response=json&amp;date=20260501&amp;stockNo=2330\" rel=\"noopener noreferrer\" target=\"_blank\">TWSE</a>）。</li>\n<li>近端支撐看 NT$2,185-2,205，較大支撐看 60 日均線約 NT$2,018；壓力看 NT$2,310 與 5 月高點 NT$2,345（來源：<a href=\"https://www.twse.com.tw/exchangeReport/STOCK_DAY?response=json&amp;date=20260501&amp;stockNo=2330\" rel=\"noopener noreferrer\" target=\"_blank\">TWSE</a>）。</li>\n</ul>\n<h2>多空辯論</h2>\n<p><strong>多方論點：</strong> 台積電仍是 AI 算力基礎設施的核心供應商。1Q26 HPC 佔營收 61%、先進製程佔 74%，公司又把 2026 年美元營收成長展望提高到 above 30%，並將 CapEx 推向 US$52-56B 區間高端，顯示訂單能見度仍強。NVIDIA Q1 FY27 data center 年增 92%、AMD Venice 進入 TSMC 2nm ramp，強化 AI GPU、CPU、ASIC 與先進封裝需求的延續性。</p>\n<p><strong>空方論點：</strong> 市場已把高成長大幅反映在股價與估值中；以 FactSet 2026 EPS 推算約 24x forward P/E，並不便宜。短線技術面雖在均線之上，但 5/21 反彈量低於 20 日均量，MACD 動能轉弱。風險集中在地緣政治、北美客戶 76% 營收集中度、海外廠與 2nm ramp 對毛利率的 2%-3% 稀釋，以及 AI 資本支出若出現遞延，估值會先修正。</p>\n<p><strong>關鍵分歧：</strong></p>\n<ul>\n<li>AI demand 是「多年結構性短缺」還是「高基期下的提前拉貨」。</li>\n<li>2nm / CoWoS 擴產能否在不明顯壓低毛利率的情況下轉化為 EPS 上修。</li>\n<li>股價能否有效突破 NT$2,310-2,345，或先回測 60 日均線消化估值。</li>\n</ul>\n<h2>風險管理員備註</h2>\n<ul>\n<li>Risk Manager 結論：APPROVES WITH ADJUSTMENT（調整後通過）。HOLD 可以接受，但不建議在量能未確認前追價轉 BUY。</li>\n<li>調整要求：若作為模型部位，應降低單一個股集中度，等待月營收、Q2 實績或放量突破確認；若已是重倉，風險應以 NT$2,185 與 60 日均線作為重新檢查點。</li>\n<li>下行情境包括：AI capex 延遲、NVIDIA / CSP 拉貨節奏放緩、台海或美中政策風險升溫、海外廠成本與 2nm ramp 稀釋毛利率高於公司目前說法。</li>\n<li>流動性不是主要問題；主要問題是高權值股對台股指數與主動 / 被動資金流高度敏感，若半導體估值修正，2330.TW 很難完全脫鉤。</li>\n</ul>\n<hr/>\n<p>⚠️ <strong>免責聲明：</strong> 本內容是根據公開資訊整理的教育性研究。\n不構成投資建議、招攬或交易建議。市場可能朝任何 thesis 的反方向波動。\n交易前請自行研究，並諮詢合格持牌顧問。此 skill 不會下任何訂單。</p>",
  "tradingViewUrl": "https://www.tradingview.com/chart/?symbol=TWSE%3A2330"
}
